Workbook

Sheet Customer_churn_data
A1: CustID | B1: Customer Name | C1: Gender | D1: Age | E1: age group | F1: City | G1: Contract Type | H1: Tenure (Months) | I1: Tenure Bucket | J1: Monthly Charges (₹) | K1: Total Charges (₹) | L1: Internet Service | M1: Signup Date | N1: Churn | O1: Churn_Flag | P1: Age_Imputed | Q1: Tenure_Imputed | R1: Monthly_Imputed | S1: Total_Imputed | T1: Needs_Review | U1: Totalkey
A2: C1001 | B2: Rahul Agarwal | C2: Male | D2: 35 | E2: =IF(D2<=25,"18-25",IF(D2<=35,"26-35",IF(D2<=45,"36-45",IF(D2<=60,"46-60","60+")))) -> 26-35 | F2: Hyderabad | G2: Month-to-month | H2: 22 | I2: =IF(H2="","Unknown",IF(H2<=6,"0-6 months",IF(H2<=12,"7-12 months",IF(H2<=24,"13-24 months",IF(H2<=48,"25-48 months","49+ months"))))) -> 13-24 months | J2: 1149 | K2: 25278 | L2: Fiber | M2: 45267 | N2: No | O2: =IF(N2="Yes",1,IF(N2="No",0,"")) -> 0 | P2: No | Q2: No | R2: No | S2: No | T2: No | U2: =IF(K2="","",K2+ROW()/1000000) -> 25278
A3: C1002 | B3: Vikram Mehta | C3: Male | D3: 32 | E3: =IF(D3<=25,"18-25",IF(D3<=35,"26-35",IF(D3<=45,"36-45",IF(D3<=60,"46-60","60+")))) -> 26-35 | F3: Jaipur | G3: One year | H3: 35 | I3: =IF(H3="","Unknown",IF(H3<=6,"0-6 months",IF(H3<=12,"7-12 months",IF(H3<=24,"13-24 months",IF(H3<=48,"25-48 months","49+ months"))))) -> 25-48 months | J3: 999 | K3: 34965 | L3: Fiber | M3: 44853 | N3: No | O3: =IF(N3="Yes",1,IF(N3="No",0,"")) -> 0 | P3: No | Q3: No | R3: No | S3: No | T3: No | U3: =IF(K3="","",K3+ROW()/1000000) -> 34965
A4: C1003 | B4: Arjun Pandey | C4: Male | D4: 47 | E4: =IF(D4<=25,"18-25",IF(D4<=35,"26-35",IF(D4<=45,"36-45",IF(D4<=60,"46-60","60+")))) -> 46-60 | F4: Pune | G4: Month-to-month | H4: 11 | I4: =IF(H4="","Unknown",IF(H4<=6,"0-6 months",IF(H4<=12,"7-12 months",IF(H4<=24,"13-24 months",IF(H4<=48,"25-48 months","49+ months"))))) -> 7-12 months | J4: 599 | K4: 6589 | L4: DSL | M4: 45571 | N4: Yes | O4: =IF(N4="Yes",1,IF(N4="No",0,"")) -> 1 | P4: Yes | Q4: No | R4: No | S4: No | T4: No | U4: =IF(K4="","",K4+ROW()/1000000) -> 6589
A5: C1004 | B5: Riya Malhotra | C5: Female | D5: 69 | E5: =IF(D5<=25,"18-25",IF(D5<=35,"26-35",IF(D5<=45,"36-45",IF(D5<=60,"46-60","60+")))) -> 60+ | F5: Delhi | G5: One year | H5: 25 | I5: =IF(H5="","Unknown",IF(H5<=6,"0-6 months",IF(H5<=12,"7-12 months",IF(H5<=24,"13-24 months",IF(H5<=48,"25-48 months","49+ months"))))) -> 25-48 months | J5: 1149 | K5: 28725 | L5: Fiber | M5: 45159 | N5: Unknown | O5: =IF(N5="Yes",1,IF(N5="No",0,"")) | P5: No | Q5: No | R5: No | S5: No | T5: Churn unknown | U5: =IF(K5="","",K5+ROW()/1000000) -> 28725
A6: C1005 | B6: Tanvi Mehta | C6: Female | D6: 63 | E6: =IF(D6<=25,"18-25",IF(D6<=35,"26-35",IF(D6<=45,"36-45",IF(D6<=60,"46-60","60+")))) -> 60+ | F6: Mumbai | G6: Month-to-month | H6: 10 | I6: =IF(H6="","Unknown",IF(H6<=6,"0-6 months",IF(H6<=12,"7-12 months",IF(H6<=24,"13-24 months",IF(H6<=48,"25-48 months","49+ months"))))) -> 7-12 months | J6: 599 | K6: 5990 | L6: DSL | M6: 45616 | N6: No | O6: =IF(N6="Yes",1,IF(N6="No",0,"")) -> 0 | P6: No | Q6: No | R6: No | S6: No | T6: No | U6: =IF(K6="","",K6+ROW()/1000000) -> 5990
A7: C1006 | B7: Shreya Chopra | C7: Female | D7: 71 | E7: =IF(D7<=25,"18-25",IF(D7<=35,"26-35",IF(D7<=45,"36-45",IF(D7<=60,"46-60","60+")))) -> 60+ | F7: Pune | G7: Month-to-month | H7: 22 | I7: =IF(H7="","Unknown",IF(H7<=6,"0-6 months",IF(H7<=12,"7-12 months",IF(H7<=24,"13-24 months",IF(H7<=48,"25-48 months","49+ months"))))) -> 13-24 months | J7: 1199 | K7: 26378 | L7: Fiber | M7: 45263 | N7: No | O7: =IF(N7="Yes",1,IF(N7="No",0,"")) -> 0 | P7: No | Q7: No | R7: No | S7: No | T7: No | U7: =IF(K7="","",K7+ROW()/1000000) -> 26378
A8: C1007 | B8: Arjun Kapoor | C8: Male | D8: 42 | E8: =IF(D8<=25,"18-25",IF(D8<=35,"26-35",IF(D8<=45,"36-45",IF(D8<=60,"46-60","60+")))) -> 36-45 | F8: Chennai | G8: Two year | H8: 72 | I8: =IF(H8="","Unknown",IF(H8<=6,"0-6 months",IF(H8<=12,"7-12 months",IF(H8<=24,"13-24 months",IF(H8<=48,"25-48 months","49+ months"))))) -> 49+ months | J8: 1199 | K8: 86328 | L8: Fiber | M8: 43744 | N8: No | O8: =IF(N8="Yes",1,IF(N8="No",0,"")) -> 0 | P8: No | Q8: No | R8: No | S8: No | T8: No | U8: =IF(K8="","",K8+ROW()/1000000) -> 86328
A9: C1008 | B9: Manish Verma | C9: Male | D9: 69 | E9: =IF(D9<=25,"18-25",IF(D9<=35,"26-35",IF(D9<=45,"36-45",IF(D9<=60,"46-60","60+")))) -> 60+ | F9: Pune | G9: Month-to-month | H9: 19 | I9: =IF(H9="","Unknown",IF(H9<=6,"0-6 months",IF(H9<=12,"7-12 months",IF(H9<=24,"13-24 months",IF(H9<=48,"25-48 months","49+ months"))))) -> 13-24 months | J9: 849 | K9: 16131 | L9: DSL | M9: 45346 | N9: No | O9: =IF(N9="Yes",1,IF(N9="No",0,"")) -> 0 | P9: No | Q9: No | R9: No | S9: No | T9: No | U9: =IF(K9="","",K9+ROW()/1000000) -> 16131
A10: C1009 | B10: Pooja Malhotra | C10: Female | D10: 26 | E10: =IF(D10<=25,"18-25",IF(D10<=35,"26-35",IF(D10<=45,"36-45",IF(D10<=60,"46-60","60+")))) -> 26-35 | F10: Hyderabad | G10: One year | H10: 38 | I10: =IF(H10="","Unknown",IF(H10<=6,"0-6 months",IF(H10<=12,"7-12 months",IF(H10<=24,"13-24 months",IF(H10<=48,"25-48 months","49+ months"))))) -> 25-48 months | J10: 1149 | K10: 43662 | L10: Fiber | M10: 44784 | N10: No | O10: =IF(N10="Yes",1,IF(N10="No",0,"")) -> 0 | P10: No | Q10: No | R10: No | S10: Yes | T10: No | U10: =IF(K10="","",K10+ROW()/1000000) -> 43662
A11: C1010 | B11: Neha Verma | C11: Female | D11: 73 | E11: =IF(D11<=25,"18-25",IF(D11<=35,"26-35",IF(D11<=45,"36-45",IF(D11<=60,"46-60","60+")))) -> 60+ | F11: Mumbai | G11: Month-to-month | H11: 22 | I11: =IF(H11="","Unknown",IF(H11<=6,"0-6 months",IF(H11<=12,"7-12 months",IF(H11<=24,"13-24 months",IF(H11<=48,"25-48 months","49+ months"))))) -> 13-24 months | J11: 749 | K11: 16478 | L11: DSL | N11: Yes | O11: =IF(N11="Yes",1,IF(N11="No",0,"")) -> 1 | P11: No | Q11: No | R11: No | S11: No | T11: Date missing | U11: =IF(K11="","",K11+ROW()/1000000) -> 16478
A12: C1011 | B12: Payal Malhotra | C12: Female | D12: 53 | E12: =IF(D12<=25,"18-25",IF(D12<=35,"26-35",IF(D12<=45,"36-45",IF(D12<=60,"46-60","60+")))) -> 46-60 | F12: Chandigarh | G12: Two year | H12: 15 | I12: =IF(H12="","Unknown",IF(H12<=6,"0-6 months",IF(H12<=12,"7-12 months",IF(H12<=24,"13-24 months",IF(H12<=48,"25-48 months","49+ months"))))) -> 13-24 months | J12: 1149 | K12: 17235 | L12: Fiber | M12: 45468 | N12: No | O12: =IF(N12="Yes",1,IF(N12="No",0,"")) -> 0 | P12: No | Q12: No | R12: No | S12: No | T12: No | U12: =IF(K12="","",K12+ROW()/1000000) -> 17235
A13: C1012 | B13: Harsh Tiwari | C13: Male | D13: 28 | E13: =IF(D13<=25,"18-25",IF(D13<=35,"26-35",IF(D13<=45,"36-45",IF(D13<=60,"46-60","60+")))) -> 26-35 | F13: Ahmedabad | G13: Month-to-month | H13: 24 | I13: =IF(H13="","Unknown",IF(H13<=6,"0-6 months",IF(H13<=12,"7-12 months",IF(H13<=24,"13-24 months",IF(H13<=48,"25-48 months","49+ months"))))) -> 13-24 months | J13: 1149 | K13: 27576 | L13: Fiber | M13: 45205 | N13: No | O13: =IF(N13="Yes",1,IF(N13="No",0,"")) -> 0 | P13: No | Q13: No | R13: No | S13: No | T13: No | U13: =IF(K13="","",K13+ROW()/1000000) -> 27576
A14: C1013 | B14: Payal Yadav | C14: Unknown | D14: 30 | E14: =IF(D14<=25,"18-25",IF(D14<=35,"26-35",IF(D14<=45,"36-45",IF(D14<=60,"46-60","60+")))) -> 26-35 | F14: Bangalore | G14: Month-to-month | H14: 17 | I14: =IF(H14="","Unknown",IF(H14<=6,"0-6 months",IF(H14<=12,"7-12 months",IF(H14<=24,"13-24 months",IF(H14<=48,"25-48 months","49+ months"))))) -> 13-24 months | J14: 599 | K14: 10183 | L14: DSL | M14: 45415 | N14: No | O14: =IF(N14="Yes",1,IF(N14="No",0,"")) -> 0 | P14: No | Q14: No | R14: No | S14: No | T14: No | U14: =IF(K14="","",K14+ROW()/1000000) -> 10183
A15: C1014 | B15: Aditi Nair | C15: Female | D15: 21 | E15: =IF(D15<=25,"18-25",IF(D15<=35,"26-35",IF(D15<=45,"36-45",IF(D15<=60,"46-60","60+")))) -> 18-25 | F15: Hyderabad | G15: Two year | H15: 11 | I15: =IF(H15="","Unknown",IF(H15<=6,"0-6 months",IF(H15<=12,"7-12 months",IF(H15<=24,"13-24 months",IF(H15<=48,"25-48 months","49+ months"))))) -> 7-12 months | J15: 349 | K15: 3839 | L15: No Internet | M15: 45581 | N15: No | O15: =IF(N15="Yes",1,IF(N15="No",0,"")) -> 0 | P15: No | Q15: No | R15: No | S15: No | T15: No | U15: =IF(K15="","",K15+ROW()/1000000) -> 3839
A16: C1015 | B16: Rohit Saxena | C16: Unknown | D16: 48 | E16: =IF(D16<=25,"18-25",IF(D16<=35,"26-35",IF(D16<=45,"36-45",IF(D16<=60,"46-60","60+")))) -> 46-60 | F16: Jaipur | G16: Month-to-month | H16: 20 | I16: =IF(H16="","Unknown",IF(H16<=6,"0-6 months",IF(H16<=12,"7-12 months",IF(H16<=24,"13-24 months",IF(H16<=48,"25-48 months","49+ months"))))) -> 13-24 months | J16: 999 | K16: 19980 | L16: Fiber | M16: 45306 | N16: No | O16: =IF(N16="Yes",1,IF(N16="No",0,"")) -> 0 | P16: No | Q16: No | R16: No | S16: No | T16: No | U16: =IF(K16="","",K16+ROW()/1000000) -> 19980
A17: C1016 | B17: Harsh Rao | C17: Male | D17: 60 | E17: =IF(D17<=25,"18-25",IF(D17<=35,"26-35",IF(D17<=45,"36-45",IF(D17<=60,"46-60","60+")))) -> 46-60 | F17: Indore | G17: Month-to-month | I17: =IF(H17="","Unknown",IF(H17<=6,"0-6 months",IF(H17<=12,"7-12 months",IF(H17<=24,"13-24 months",IF(H17<=48,"25-48 months","49+ months"))))) -> Unknown | K17: 5985 | L17: No Internet | M17: 45478 | N17: Yes | O17: =IF(N17="Yes",1,IF(N17="No",0,"")) -> 1 | P17: No | Q17: No | R17: No | S17: No | T17: Monthly missing; Tenure missing | U17: =IF(K17="","",K17+ROW()/1000000) -> 5985
A18: C1017 | B18: Rajesh Nair | C18: Male | D18: 18 | E18: =IF(D18<=25,"18-25",IF(D18<=35,"26-35",IF(D18<=45,"36-45",IF(D18<=60,"46-60","60+")))) -> 18-25 | F18: Mumbai | G18: One year | H18: 5 | I18: =IF(H18="","Unknown",IF(H18<=6,"0-6 months",IF(H18<=12,"7-12 months",IF(H18<=24,"13-24 months",IF(H18<=48,"25-48 months","49+ months"))))) -> 0-6 months | J18: 599 | K18: 2995 | L18: DSL | M18: 45771 | N18: Yes | O18: =IF(N18="Yes",1,IF(N18="No",0,"")) -> 1 | P18: No | Q18: No | R18: No | S18: No | T18: No | U18: =IF(K18="","",K18+ROW()/1000000) -> 2995
A19: C1018 | B19: Komal Mehta | C19: Female | D19: 52 | E19: =IF(D19<=25,"18-25",IF(D19<=35,"26-35",IF(D19<=45,"36-45",IF(D19<=60,"46-60","60+")))) -> 46-60 | F19: Bangalore | G19: One year | H19: 37 | I19: =IF(H19="","Unknown",IF(H19<=6,"0-6 months",IF(H19<=12,"7-12 months",IF(H19<=24,"13-24 months",IF(H19<=48,"25-48 months","49+ months"))))) -> 25-48 months | J19: 499 | K19: 18463 | L19: No Internet | M19: 44812 | N19: No | O19: =IF(N19="Yes",1,IF(N19="No",0,"")) -> 0 | P19: No | Q19: No | R19: No | S19: No | T19: No | U19: =IF(K19="","",K19+ROW()/1000000) -> 18463
A20: C1019 | B20: Karan Saxena | C20: Male | D20: 45 | E20: =IF(D20<=25,"18-25",IF(D20<=35,"26-35",IF(D20<=45,"36-45",IF(D20<=60,"46-60","60+")))) -> 36-45 | F20: Pune | G20: Month-to-month | H20: 24 | I20: =IF(H20="","Unknown",IF(H20<=6,"0-6 months",IF(H20<=12,"7-12 months",IF(H20<=24,"13-24 months",IF(H20<=48,"25-48 months","49+ months"))))) -> 13-24 months | J20: 1199 | K20: 28776 | L20: Fiber | M20: 45185 | N20: Yes | O20: =IF(N20="Yes",1,IF(N20="No",0,"")) -> 1 | P20: No | Q20: No | R20: No | S20: No | T20: No | U20: =IF(K20="","",K20+ROW()/1000000) -> 28776
A21: C1020 | B21: Anjali Nair | C21: Female | D21: 30 | E21: =IF(D21<=25,"18-25",IF(D21<=35,"26-35",IF(D21<=45,"36-45",IF(D21<=60,"46-60","60+")))) -> 26-35 | F21: Hyderabad | G21: Month-to-month | H21: 6 | I21: =IF(H21="","Unknown",IF(H21<=6,"0-6 months",IF(H21<=12,"7-12 months",IF(H21<=24,"13-24 months",IF(H21<=48,"25-48 months","49+ months"))))) -> 0-6 months | J21: 699 | K21: 4194 | L21: DSL | M21: 45746 | N21: No | O21: =IF(N21="Yes",1,IF(N21="No",0,"")) -> 0 | P21: No | Q21: No | R21: No | S21: Yes | T21: No | U21: =IF(K21="","",K21+ROW()/1000000) -> 4194
A22: C1021 | B22: Sonal Reddy | C22: Female | D22: 21 | E22: =IF(D22<=25,"18-25",IF(D22<=35,"26-35",IF(D22<=45,"36-45",IF(D22<=60,"46-60","60+")))) -> 18-25 | F22: Indore | G22: Two year | H22: 12 | I22: =IF(H22="","Unknown",IF(H22<=6,"0-6 months",IF(H22<=12,"7-12 months",IF(H22<=24,"13-24 months",IF(H22<=48,"25-48 months","49+ months"))))) -> 7-12 months | J22: 399 | K22: 4788 | L22: No Internet | M22: 45553 | N22: No | O22: =IF(N22="Yes",1,IF(N22="No",0,"")) -> 0 | P22: No | Q22: No | R22: No | S22: Yes | T22: No | U22: =IF(K22="","",K22+ROW()/1000000) -> 4788
A23: C1022 | B23: Deepika Rao | C23: Female | D23: 75 | E23: =IF(D23<=25,"18-25",IF(D23<=35,"26-35",IF(D23<=45,"36-45",IF(D23<=60,"46-60","60+")))) -> 60+ | F23: Delhi | G23: Month-to-month | H23: 13 | I23: =IF(H23="","Unknown",IF(H23<=6,"0-6 months",IF(H23<=12,"7-12 months",IF(H23<=24,"13-24 months",IF(H23<=48,"25-48 months","49+ months"))))) -> 13-24 months | J23: 699 | K23: 9087 | L23: DSL | M23: 45516 | N23: Yes | O23: =IF(N23="Yes",1,IF(N23="No",0,"")) -> 1 | P23: No | Q23: No | R23: No | S23: No | T23: No | U23: =IF(K23="","",K23+ROW()/1000000) -> 9087
A24: C1023 | B24: Pooja Mehta | C24: Female | D24: 36 | E24: =IF(D24<=25,"18-25",IF(D24<=35,"26-35",IF(D24<=45,"36-45",IF(D24<=60,"46-60","60+")))) -> 36-45 | F24: Hyderabad | G24: Two year | H24: 70 | I24: =IF(H24="","Unknown",IF(H24<=6,"0-6 months",IF(H24<=12,"7-12 months",IF(H24<=24,"13-24 months",IF(H24<=48,"25-48 months","49+ months"))))) -> 49+ months | J24: 1199 | K24: 83930 | L24: Fiber | M24: 43810 | N24: Yes | O24: =IF(N24="Yes",1,IF(N24="No",0,"")) -> 1 | P24: No | Q24: No | R24: No | S24: No | T24: No | U24: =IF(K24="","",K24+ROW()/1000000) -> 83930
A25: C1024 | B25: Payal Jain | C25: Female | D25: 28 | E25: =IF(D25<=25,"18-25",IF(D25<=35,"26-35",IF(D25<=45,"36-45",IF(D25<=60,"46-60","60+")))) -> 26-35 | F25: Unknown | G25: Two year | H25: 24 | I25: =IF(H25="","Unknown",IF(H25<=6,"0-6 months",IF(H25<=12,"7-12 months",IF(H25<=24,"13-24 months",IF(H25<=48,"25-48 months","49+ months"))))) -> 13-24 months | J25: 599 | K25: 14376 | L25: DSL | M25: 45201 | N25: No | O25: =IF(N25="Yes",1,IF(N25="No",0,"")) -> 0 | P25: No | Q25: No | R25: No | S25: No | T25: No | U25: =IF(K25="","",K25+ROW()/1000000) -> 14376
A26: C1025 | B26: Anjali Bose | C26: Female | D26: 33 | E26: =IF(D26<=25,"18-25",IF(D26<=35,"26-35",IF(D26<=45,"36-45",IF(D26<=60,"46-60","60+")))) -> 26-35 | F26: Lucknow | G26: One year | H26: 27 | I26: =IF(H26="","Unknown",IF(H26<=6,"0-6 months",IF(H26<=12,"7-12 months",IF(H26<=24,"13-24 months",IF(H26<=48,"25-48 months","49+ months"))))) -> 25-48 months | J26: 1149 | K26: 31023 | L26: Fiber | M26: 45089 | N26: No | O26: =IF(N26="Yes",1,IF(N26="No",0,"")) -> 0 | P26: No | Q26: No | R26: No | S26: No | T26: No | U26: =IF(K26="","",K26+ROW()/1000000) -> 31023
A27: C1026 | B27: Deepika Saxena | C27: Female | D27: 63 | E27: =IF(D27<=25,"18-25",IF(D27<=35,"26-35",IF(D27<=45,"36-45",IF(D27<=60,"46-60","60+")))) -> 60+ | F27: Pune | G27: Month-to-month | H27: 22 | I27: =IF(H27="","Unknown",IF(H27<=6,"0-6 months",IF(H27<=12,"7-12 months",IF(H27<=24,"13-24 months",IF(H27<=48,"25-48 months","49+ months"))))) -> 13-24 months | J27: 1049 | K27: 23078 | L27: Fiber | N27: Yes | O27: =IF(N27="Yes",1,IF(N27="No",0,"")) -> 1 | P27: No | Q27: No | R27: No | S27: No | T27: Date missing | U27: =IF(K27="","",K27+ROW()/1000000) -> 23078
A28: C1027 | B28: Rahul Kapoor | C28: Male | D28: 57 | E28: =IF(D28<=25,"18-25",IF(D28<=35,"26-35",IF(D28<=45,"36-45",IF(D28<=60,"46-60","60+")))) -> 46-60 | F28: Lucknow | G28: Two year | H28: 28 | I28: =IF(H28="","Unknown",IF(H28<=6,"0-6 months",IF(H28<=12,"7-12 months",IF(H28<=24,"13-24 months",IF(H28<=48,"25-48 months","49+ months"))))) -> 25-48 months | J28: 799 | K28: 22372 | L28: DSL | M28: 45060 | N28: No | O28: =IF(N28="Yes",1,IF(N28="No",0,"")) -> 0 | P28: No | Q28: No | R28: No | S28: No | T28: No | U28: =IF(K28="","",K28+ROW()/1000000) -> 22372
A29: C1028 | B29: Unknown | C29: Male | D29: 36 | E29: =IF(D29<=25,"18-25",IF(D29<=35,"26-35",IF(D29<=45,"36-45",IF(D29<=60,"46-60","60+")))) -> 36-45 | F29: Bangalore | G29: Month-to-month | H29: 10 | I29: =IF(H29="","Unknown",IF(H29<=6,"0-6 months",IF(H29<=12,"7-12 months",IF(H29<=24,"13-24 months",IF(H29<=48,"25-48 months","49+ months"))))) -> 7-12 months | J29: 1299 | K29: 12990 | L29: Fiber | M29: 45602 | N29: Yes | O29: =IF(N29="Yes",1,IF(N29="No",0,"")) -> 1 | P29: No | Q29: No | R29: No | S29: No | T29: No | U29: =IF(K29="","",K29+ROW()/1000000) -> 12990
A30: C1029 | B30: Anjali Singh | C30: Female | D30: 34 | E30: =IF(D30<=25,"18-25",IF(D30<=35,"26-35",IF(D30<=45,"36-45",IF(D30<=60,"46-60","60+")))) -> 26-35 | F30: Mumbai | G30: Two year | H30: 20 | I30: =IF(H30="","Unknown",IF(H30<=6,"0-6 months",IF(H30<=12,"7-12 months",IF(H30<=24,"13-24 months",IF(H30<=48,"25-48 months","49+ months"))))) -> 13-24 months | J30: 1049 | K30: 20980 | L30: Fiber | N30: No | O30: =IF(N30="Yes",1,IF(N30="No",0,"")) -> 0 | P30: No | Q30: Yes | R30: No | S30: No | T30: Date missing | U30: =IF(K30="","",K30+ROW()/1000000) -> 20980
A31: C1030 | B31: Suresh Jain | C31: Male | D31: 49 | E31: =IF(D31<=25,"18-25",IF(D31<=35,"26-35",IF(D31<=45,"36-45",IF(D31<=60,"46-60","60+")))) -> 46-60 | F31: Chennai | G31: Unknown | H31: 12 | I31: =IF(H31="","Unknown",IF(H31<=6,"0-6 months",IF(H31<=12,"7-12 months",IF(H31<=24,"13-24 months",IF(H31<=48,"25-48 months","49+ months"))))) -> 7-12 months | J31: 449 | K31: 5388 | L31: No Internet | M31: 45558 | N31: Yes | O31: =IF(N31="Yes",1,IF(N31="No",0,"")) -> 1 | P31: No | Q31: No | R31: No | S31: No | T31: No | U31: =IF(K31="","",K31+ROW()/1000000) -> 5388
A32: C1031 | B32: Suresh Gupta | C32: Male | D32: 65 | E32: =IF(D32<=25,"18-25",IF(D32<=35,"26-35",IF(D32<=45,"36-45",IF(D32<=60,"46-60","60+")))) -> 60+ | F32: Ahmedabad | G32: One year | H32: 1 | I32: =IF(H32="","Unknown",IF(H32<=6,"0-6 months",IF(H32<=12,"7-12 months",IF(H32<=24,"13-24 months",IF(H32<=48,"25-48 months","49+ months"))))) -> 0-6 months | J32: 899 | K32: 899 | L32: Fiber | M32: 45872 | N32: No | O32: =IF(N32="Yes",1,IF(N32="No",0,"")) -> 0 | P32: No | Q32: No | R32: No | S32: Yes | T32: No | U32: =IF(K32="","",K32+ROW()/1000000) -> 899.00003
A33: C1032 | B33: Tanvi Mishra | C33: Female | D33: 27 | E33: =IF(D33<=25,"18-25",IF(D33<=35,"26-35",IF(D33<=45,"36-45",IF(D33<=60,"46-60","60+")))) -> 26-35 | F33: Kolkata | G33: Month-to-month | H33: 2 | I33: =IF(H33="","Unknown",IF(H33<=6,"0-6 months",IF(H33<=12,"7-12 months",IF(H33<=24,"13-24 months",IF(H33<=48,"25-48 months","49+ months"))))) -> 0-6 months | J33: 699 | K33: 1398 | L33: DSL | M33: 45857 | N33: No | O33: =IF(N33="Yes",1,IF(N33="No",0,"")) -> 0 | P33: No | Q33: No | R33: No | S33: No | T33: No | U33: =IF(K33="","",K33+ROW()/1000000) -> 1398
A34: C1033 | B34: Riya Agarwal | C34: Female | D34: 27 | E34: =IF(D34<=25,"18-25",IF(D34<=35,"26-35",IF(D34<=45,"36-45",IF(D34<=60,"46-60","60+")))) -> 26-35 | F34: Hyderabad | G34: Two year | H34: 23 | I34: =IF(H34="","Unknown",IF(H34<=6,"0-6 months",IF(H34<=12,"7-12 months",IF(H34<=24,"13-24 months",IF(H34<=48,"25-48 months","49+ months"))))) -> 13-24 months | J34: 399 | K34: 9177 | L34: No Internet | M34: 45228 | N34: No | O34: =IF(N34="Yes",1,IF(N34="No",0,"")) -> 0 | P34: No | Q34: No | R34: No | S34: No | T34: No | U34: =IF(K34="","",K34+ROW()/1000000) -> 9177
A35: C1034 | B35: Ritu Malhotra | C35: Female | D35: 28 | E35: =IF(D35<=25,"18-25",IF(D35<=35,"26-35",IF(D35<=45,"36-45",IF(D35<=60,"46-60","60+")))) -> 26-35 | F35: Kochi | G35: One year | H35: 3 | I35: =IF(H35="","Unknown",IF(H35<=6,"0-6 months",IF(H35<=12,"7-12 months",IF(H35<=24,"13-24 months",IF(H35<=48,"25-48 months","49+ months"))))) -> 0-6 months | J35: 1099 | K35: 3297 | L35: Fiber | M35: 45809 | N35: Yes | O35: =IF(N35="Yes",1,IF(N35="No",0,"")) -> 1 | P35: No | Q35: No | R35: No | S35: No | T35: No | U35: =IF(K35="","",K35+ROW()/1000000) -> 3297
A36: C1035 | B36: Isha Iyer | C36: Female | D36: 70 | E36: =IF(D36<=25,"18-25",IF(D36<=35,"26-35",IF(D36<=45,"36-45",IF(D36<=60,"46-60","60+")))) -> 60+ | F36: Kochi | G36: Two year | H36: 25 | I36: =IF(H36="","Unknown",IF(H36<=6,"0-6 months",IF(H36<=12,"7-12 months",IF(H36<=24,"13-24 months",IF(H36<=48,"25-48 months","49+ months"))))) -> 25-48 months | J36: 749 | K36: 18725 | L36: DSL | M36: 45154 | N36: No | O36: =IF(N36="Yes",1,IF(N36="No",0,"")) -> 0 | P36: No | Q36: No | R36: No | S36: No | T36: No | U36: =IF(K36="","",K36+ROW()/1000000) -> 18725
A37: C1036 | B37: Isha Chopra | C37: Female | D37: 50 | E37: =IF(D37<=25,"18-25",IF(D37<=35,"26-35",IF(D37<=45,"36-45",IF(D37<=60,"46-60","60+")))) -> 46-60 | F37: Kolkata | G37: One year | H37: 22 | I37: =IF(H37="","Unknown",IF(H37<=6,"0-6 months",IF(H37<=12,"7-12 months",IF(H37<=24,"13-24 months",IF(H37<=48,"25-48 months","49+ months"))))) -> 13-24 months | J37: 449 | K37: 9878 | L37: No Internet | M37: 45260 | N37: No | O37: =IF(N37="Yes",1,IF(N37="No",0,"")) -> 0 | P37: No | Q37: No | R37: No | S37: No | T37: No | U37: =IF(K37="","",K37+ROW()/1000000) -> 9878
A38: C1037 | B38: Karan Yadav | C38: Male | D38: 45 | E38: =IF(D38<=25,"18-25",IF(D38<=35,"26-35",IF(D38<=45,"36-45",IF(D38<=60,"46-60","60+")))) -> 36-45 | F38: Pune | G38: One year | H38: 39 | I38: =IF(H38="","Unknown",IF(H38<=6,"0-6 months",IF(H38<=12,"7-12 months",IF(H38<=24,"13-24 months",IF(H38<=48,"25-48 months","49+ months"))))) -> 25-48 months | J38: 799 | K38: 31161 | L38: DSL | M38: 44752 | N38: No | O38: =IF(N38="Yes",1,IF(N38="No",0,"")) -> 0 | P38: No | Q38: No | R38: No | S38: No | T38: No | U38: =IF(K38="","",K38+ROW()/1000000) -> 31161
A39: C1038 | B39: Sneha Pandey | C39: Female | D39: 45 | E39: =IF(D39<=25,"18-25",IF(D39<=35,"26-35",IF(D39<=45,"36-45",IF(D39<=60,"46-60","60+")))) -> 36-45 | F39: Delhi | G39: Month-to-month | H39: 22 | I39: =IF(H39="","Unknown",IF(H39<=6,"0-6 months",IF(H39<=12,"7-12 months",IF(H39<=24,"13-24 months",IF(H39<=48,"25-48 months","49+ months"))))) -> 13-24 months | J39: 399 | K39: 8778 | L39: No Internet | M39: 45266 | N39: Yes | O39: =IF(N39="Yes",1,IF(N39="No",0,"")) -> 1 | P39: No | Q39: No | R39: Yes | S39: No | T39: No | U39: =IF(K39="","",K39+ROW()/1000000) -> 8778
A40: C1039 | B40: Riya Joshi | C40: Female | D40: 60 | E40: =IF(D40<=25,"18-25",IF(D40<=35,"26-35",IF(D40<=45,"36-45",IF(D40<=60,"46-60","60+")))) -> 46-60 | F40: Chandigarh | G40: Month-to-month | H40: 17 | I40: =IF(H40="","Unknown",IF(H40<=6,"0-6 months",IF(H40<=12,"7-12 months",IF(H40<=24,"13-24 months",IF(H40<=48,"25-48 months","49+ months"))))) -> 13-24 months | J40: 499 | K40: 8483 | L40: No Internet | M40: 45396 | N40: Yes | O40: =IF(N40="Yes",1,IF(N40="No",0,"")) -> 1 | P40: No | Q40: Yes | R40: No | S40: No | T40: No | U40: =IF(K40="","",K40+ROW()/1000000) -> 8483
A41: C1040 | B41: Sonal Singh | C41: Female | D41: 30 | E41: =IF(D41<=25,"18-25",IF(D41<=35,"26-35",IF(D41<=45,"36-45",IF(D41<=60,"46-60","60+")))) -> 26-35 | F41: Kolkata | G41: One year | H41: 12 | I41: =IF(H41="","Unknown",IF(H41<=6,"0-6 months",IF(H41<=12,"7-12 months",IF(H41<=24,"13-24 months",IF(H41<=48,"25-48 months","49+ months"))))) -> 7-12 months | J41: 1149 | K41: 13788 | L41: Fiber | M41: 45542 | N41: No | O41: =IF(N41="Yes",1,IF(N41="No",0,"")) -> 0 | P41: No | Q41: Yes | R41: No | S41: No | T41: No | U41: =IF(K41="","",K41+ROW()/1000000) -> 13788
A42: C1041 | B42: Harsh Iyer | C42: Male | D42: 31 | E42: =IF(D42<=25,"18-25",IF(D42<=35,"26-35",IF(D42<=45,"36-45",IF(D42<=60,"46-60","60+")))) -> 26-35 | F42: Kolkata | G42: One year | H42: 21 | I42: =IF(H42="","Unknown",IF(H42<=6,"0-6 months",IF(H42<=12,"7-12 months",IF(H42<=24,"13-24 months",IF(H42<=48,"25-48 months","49+ months"))))) -> 13-24 months | J42: 1099 | K42: 23079 | L42: Fiber | M42: 45282 | N42: No | O42: =IF(N42="Yes",1,IF(N42="No",0,"")) -> 0 | P42: No | Q42: No | R42: No | S42: No | T42: No | U42: =IF(K42="","",K42+ROW()/1000000) -> 23079
... A51: C1050 | B51: Nisha Mishra | C51: Female | D51: 65 | E51: =IF(D51<=25,"18-25",IF(D51<=35,"26-35",IF(D51<=45,"36-45",IF(D51<=60,"46-60","60+")))) -> 60+ | F51: Bhopal | G51: Month-to-month | H51: 8 | I51: =IF(H51="","Unknown",IF(H51<=6,"0-6 months",IF(H51<=12,"7-12 months",IF(H51<=24,"13-24 months",IF(H51<=48,"25-48 months","49+ months"))))) -> 7-12 months | J51: 999 | K51: 7992 | L51: Fiber | M51: 45688 | N51: Yes | O51: =IF(N51="Yes",1,IF(N51="No",0,"")) -> 1 | P51: No | Q51: No | R51: No | S51: No | T51: No | U51: =IF(K51="","",K51+ROW()/1000000) -> 7992.0001
A52: C1051 | B52: Swati Saxena | C52: Female | D52: 61 | E52: =IF(D52<=25,"18-25",IF(D52<=35,"26-35",IF(D52<=45,"36-45",IF(D52<=60,"46-60","60+")))) -> 60+ | F52: Kochi | G52: Month-to-month | I52: =IF(H52="","Unknown",IF(H52<=6,"0-6 months",IF(H52<=12,"7-12 months",IF(H52<=24,"13-24 months",IF(H52<=48,"25-48 months","49+ months"))))) -> Unknown | K52: 9735 | L52: DSL | M52: 45466 | N52: Yes | O52: =IF(N52="Yes",1,IF(N52="No",0,"")) -> 1 | P52: No | Q52: No | R52: No | S52: No | T52: Monthly missing; Tenure missing | U52: =IF(K52="","",K52+ROW()/1000000) -> 9735.0001
A53: C1052 | B53: Vikram Chopra | C53: Male | D53: 45 | E53: =IF(D53<=25,"18-25",IF(D53<=35,"26-35",IF(D53<=45,"36-45",IF(D53<=60,"46-60","60+")))) -> 36-45 | F53: Bangalore | G53: Two year | H53: 34 | I53: =IF(H53="","Unknown",IF(H53<=6,"0-6 months",IF(H53<=12,"7-12 months",IF(H53<=24,"13-24 months",IF(H53<=48,"25-48 months","49+ months"))))) -> 25-48 months | J53: 749 | K53: 25466 | L53: DSL | M53: 44898 | N53: No | O53: =IF(N53="Yes",1,IF(N53="No",0,"")) -> 0 | P53: No | Q53: No | R53: No | S53: No | T53: No | U53: =IF(K53="","",K53+ROW()/1000000) -> 25466
A54: C1053 | B54: Kavita Tiwari | C54: Female | D54: 34 | E54: =IF(D54<=25,"18-25",IF(D54<=35,"26-35",IF(D54<=45,"36-45",IF(D54<=60,"46-60","60+")))) -> 26-35 | F54: Chandigarh | G54: Month-to-month | H54: 18 | I54: =IF(H54="","Unknown",IF(H54<=6,"0-6 months",IF(H54<=12,"7-12 months",IF(H54<=24,"13-24 months",IF(H54<=48,"25-48 months","49+ months"))))) -> 13-24 months | J54: 599 | K54: 10782 | L54: DSL | M54: 45364 | N54: No | O54: =IF(N54="Yes",1,IF(N54="No",0,"")) -> 0 | P54: No | Q54: No | R54: No | S54: No | T54: No | U54: =IF(K54="","",K54+ROW()/1000000) -> 10782
A55: C1054 | B55: Rahul Nair | C55: Male | D55: 30 | E55: =IF(D55<=25,"18-25",IF(D55<=35,"26-35",IF(D55<=45,"36-45",IF(D55<=60,"46-60","60+")))) -> 26-35 | F55: Chandigarh | G55: Month-to-month | H55: 5 | I55: =IF(H55="","Unknown",IF(H55<=6,"0-6 months",IF(H55<=12,"7-12 months",IF(H55<=24,"13-24 months",IF(H55<=48,"25-48 months","49+ months"))))) -> 0-6 months | J55: 749 | K55: 3745 | L55: DSL | M55: 45772 | N55: Yes | O55: =IF(N55="Yes",1,IF(N55="No",0,"")) -> 1 | P55: No | Q55: No | R55: No | S55: No | T55: No | U55: =IF(K55="","",K55+ROW()/1000000) -> 3745.0001
A56: C1055 | B56: Kavita Patel | C56: Unknown | D56: 28 | E56: =IF(D56<=25,"18-25",IF(D56<=35,"26-35",IF(D56<=45,"36-45",IF(D56<=60,"46-60","60+")))) -> 26-35 | F56: Lucknow | G56: One year | H56: 8 | I56: =IF(H56="","Unknown",IF(H56<=6,"0-6 months",IF(H56<=12,"7-12 months",IF(H56<=24,"13-24 months",IF(H56<=48,"25-48 months","49+ months"))))) -> 7-12 months | J56: 1299 | K56: 10392 | L56: Fiber | M56: 45685 | N56: Unknown | O56: =IF(N56="Yes",1,IF(N56="No",0,"")) | P56: No | Q56: No | R56: No | S56: No | T56: Churn unknown | U56: =IF(K56="","",K56+ROW()/1000000) -> 10392
A57: C1056 | B57: Harsh Bose | C57: Male | D57: 61 | E57: =IF(D57<=25,"18-25",IF(D57<=35,"26-35",IF(D57<=45,"36-45",IF(D57<=60,"46-60","60+")))) -> 60+ | F57: Kolkata | G57: Month-to-month | H57: 3 | I57: =IF(H57="","Unknown",IF(H57<=6,"0-6 months",IF(H57<=12,"7-12 months",IF(H57<=24,"13-24 months",IF(H57<=48,"25-48 months","49+ months"))))) -> 0-6 months | J57: 1199 | K57: 3597 | L57: Fiber | M57: 45814 | N57: Yes | O57: =IF(N57="Yes",1,IF(N57="No",0,"")) -> 1 | P57: No | Q57: No | R57: No | S57: Yes | T57: No | U57: =IF(K57="","",K57+ROW()/1000000) -> 3597.0001
A58: C1057 | B58: Riya Reddy | C58: Female | D58: 68 | E58: =IF(D58<=25,"18-25",IF(D58<=35,"26-35",IF(D58<=45,"36-45",IF(D58<=60,"46-60","60+")))) -> 60+ | F58: Lucknow | G58: One year | H58: 28 | I58: =IF(H58="","Unknown",IF(H58<=6,"0-6 months",IF(H58<=12,"7-12 months",IF(H58<=24,"13-24 months",IF(H58<=48,"25-48 months","49+ months"))))) -> 25-48 months | J58: 849 | K58: 23772 | L58: DSL | M58: 45078 | N58: No | O58: =IF(N58="Yes",1,IF(N58="No",0,"")) -> 0 | P58: No | Q58: No | R58: No | S58: No | T58: No | U58: =IF(K58="","",K58+ROW()/1000000) -> 23772
A59: C1058 | B59: Vivek Desai | C59: Male | D59: 24 | E59: =IF(D59<=25,"18-25",IF(D59<=35,"26-35",IF(D59<=45,"36-45",IF(D59<=60,"46-60","60+")))) -> 18-25 | F59: Kolkata | G59: Two year | H59: 59 | I59: =IF(H59="","Unknown",IF(H59<=6,"0-6 months",IF(H59<=12,"7-12 months",IF(H59<=24,"13-24 months",IF(H59<=48,"25-48 months","49+ months"))))) -> 49+ months | J59: 999 | K59: 58941 | L59: Fiber | M59: 44142 | N59: No | O59: =IF(N59="Yes",1,IF(N59="No",0,"")) -> 0 | P59: No | Q59: No | R59: No | S59: No | T59: No | U59: =IF(K59="","",K59+ROW()/1000000) -> 58941
A60: C1059 | B60: Riya Mishra | C60: Female | D60: 67 | E60: =IF(D60<=25,"18-25",IF(D60<=35,"26-35",IF(D60<=45,"36-45",IF(D60<=60,"46-60","60+")))) -> 60+ | F60: Ahmedabad | G60: Month-to-month | H60: 19 | I60: =IF(H60="","Unknown",IF(H60<=6,"0-6 months",IF(H60<=12,"7-12 months",IF(H60<=24,"13-24 months",IF(H60<=48,"25-48 months","49+ months"))))) -> 13-24 months | J60: 399 | K60: 7581 | L60: No Internet | M60: 45356 | N60: No | O60: =IF(N60="Yes",1,IF(N60="No",0,"")) -> 0 | P60: No | Q60: No | R60: No | S60: No | T60: No | U60: =IF(K60="","",K60+ROW()/1000000) -> 7581.0001
A61: C1060 | B61: Shreya Nair | C61: Female | D61: 66 | E61: =IF(D61<=25,"18-25",IF(D61<=35,"26-35",IF(D61<=45,"36-45",IF(D61<=60,"46-60","60+")))) -> 60+ | F61: Ahmedabad | G61: One year | H61: 22 | I61: =IF(H61="","Unknown",IF(H61<=6,"0-6 months",IF(H61<=12,"7-12 months",IF(H61<=24,"13-24 months",IF(H61<=48,"25-48 months","49+ months"))))) -> 13-24 months | J61: 1099 | K61: 24178 | L61: Fiber | M61: 45262 | N61: Yes | O61: =IF(N61="Yes",1,IF(N61="No",0,"")) -> 1 | P61: No | Q61: No | R61: Yes | S61: No | T61: No | U61: =IF(K61="","",K61+ROW()/1000000) -> 24178
A62: C1061 | B62: Unknown | C62: Unknown | D62: 35 | E62: =IF(D62<=25,"18-25",IF(D62<=35,"26-35",IF(D62<=45,"36-45",IF(D62<=60,"46-60","60+")))) -> 26-35 | F62: Lucknow | G62: One year | H62: 1 | I62: =IF(H62="","Unknown",IF(H62<=6,"0-6 months",IF(H62<=12,"7-12 months",IF(H62<=24,"13-24 months",IF(H62<=48,"25-48 months","49+ months"))))) -> 0-6 months | J62: 799 | K62: 799 | L62: DSL | M62: 45885 | N62: Yes | O62: =IF(N62="Yes",1,IF(N62="No",0,"")) -> 1 | P62: No | Q62: No | R62: No | S62: No | T62: No | U62: =IF(K62="","",K62+ROW()/1000000) -> 799.00006
A63: C1062 | B63: Sonal Nair | C63: Female | D63: 62 | E63: =IF(D63<=25,"18-25",IF(D63<=35,"26-35",IF(D63<=45,"36-45",IF(D63<=60,"46-60","60+")))) -> 60+ | F63: Ahmedabad | G63: One year | H63: 2 | I63: =IF(H63="","Unknown",IF(H63<=6,"0-6 months",IF(H63<=12,"7-12 months",IF(H63<=24,"13-24 months",IF(H63<=48,"25-48 months","49+ months"))))) -> 0-6 months | J63: 1049 | K63: 2098 | L63: Fiber | M63: 45861 | N63: No | O63: =IF(N63="Yes",1,IF(N63="No",0,"")) -> 0 | P63: No | Q63: No | R63: No | S63: No | T63: No | U63: =IF(K63="","",K63+ROW()/1000000) -> 2098.0001
A64: C1063 | B64: Tanvi Patel | C64: Female | D64: 48 | E64: =IF(D64<=25,"18-25",IF(D64<=35,"26-35",IF(D64<=45,"36-45",IF(D64<=60,"46-60","60+")))) -> 46-60 | F64: Jaipur | G64: Month-to-month | H64: 24 | I64: =IF(H64="","Unknown",IF(H64<=6,"0-6 months",IF(H64<=12,"7-12 months",IF(H64<=24,"13-24 months",IF(H64<=48,"25-48 months","49+ months"))))) -> 13-24 months | J64: 1049 | K64: 25176 | L64: Fiber | M64: 45200 | N64: No | O64: =IF(N64="Yes",1,IF(N64="No",0,"")) -> 0 | P64: No | Q64: No | R64: No | S64: No | T64: No | U64: =IF(K64="","",K64+ROW()/1000000) -> 25176
... A70: C1069 | B70: Riya Yadav | C70: Female | D70: 68 | E70: =IF(D70<=25,"18-25",IF(D70<=35,"26-35",IF(D70<=45,"36-45",IF(D70<=60,"46-60","60+")))) -> 60+ | F70: Lucknow | G70: Month-to-month | H70: 15 | I70: =IF(H70="","Unknown",IF(H70<=6,"0-6 months",IF(H70<=12,"7-12 months",IF(H70<=24,"13-24 months",IF(H70<=48,"25-48 months","49+ months"))))) -> 13-24 months | J70: 1049 | K70: 15735 | L70: Fiber | M70: 45469 | N70: No | O70: =IF(N70="Yes",1,IF(N70="No",0,"")) -> 0 | P70: No | Q70: No | R70: No | S70: No | T70: No | U70: =IF(K70="","",K70+ROW()/1000000) -> 15735
A71: C1070 | B71: Pankaj Agarwal | C71: Male | D71: 24 | E71: =IF(D71<=25,"18-25",IF(D71<=35,"26-35",IF(D71<=45,"36-45",IF(D71<=60,"46-60","60+")))) -> 18-25 | F71: Kochi | G71: Month-to-month | H71: 22 | I71: =IF(H71="","Unknown",IF(H71<=6,"0-6 months",IF(H71<=12,"7-12 months",IF(H71<=24,"13-24 months",IF(H71<=48,"25-48 months","49+ months"))))) -> 13-24 months | J71: 599 | K71: 13178 | L71: DSL | N71: Yes | O71: =IF(N71="Yes",1,IF(N71="No",0,"")) -> 1 | P71: No | Q71: No | R71: No | S71: Yes | T71: Date missing | U71: =IF(K71="","",K71+ROW()/1000000) -> 13178
A72: C1071 | B72: Rahul Tiwari | C72: Male | D72: 46 | E72: =IF(D72<=25,"18-25",IF(D72<=35,"26-35",IF(D72<=45,"36-45",IF(D72<=60,"46-60","60+")))) -> 46-60 | F72: Bhopal | G72: One year | H72: 15 | I72: =IF(H72="","Unknown",IF(H72<=6,"0-6 months",IF(H72<=12,"7-12 months",IF(H72<=24,"13-24 months",IF(H72<=48,"25-48 months","49+ months"))))) -> 13-24 months | J72: 699 | K72: 10485 | L72: DSL | M72: 45464 | N72: No | O72: =IF(N72="Yes",1,IF(N72="No",0,"")) -> 0 | P72: No | Q72: No | R72: No | S72: No | T72: No | U72: =IF(K72="","",K72+ROW()/1000000) -> 10485
A73: C1072 | B73: Manish Malhotra | C73: Male | D73: 68 | E73: =IF(D73<=25,"18-25",IF(D73<=35,"26-35",IF(D73<=45,"36-45",IF(D73<=60,"46-60","60+")))) -> 60+ | F73: Kochi | G73: One year | H73: 13 | I73: =IF(H73="","Unknown",IF(H73<=6,"0-6 months",IF(H73<=12,"7-12 months",IF(H73<=24,"13-24 months",IF(H73<=48,"25-48 months","49+ months"))))) -> 13-24 months | J73: 899 | K73: 11687 | L73: Fiber | M73: 45534 | N73: No | O73: =IF(N73="Yes",1,IF(N73="No",0,"")) -> 0 | P73: No | Q73: No | R73: No | S73: No | T73: No | U73: =IF(K73="","",K73+ROW()/1000000) -> 11687
A74: C1073 | B74: Pooja Kumar | C74: Female | D74: 21 | E74: =IF(D74<=25,"18-25",IF(D74<=35,"26-35",IF(D74<=45,"36-45",IF(D74<=60,"46-60","60+")))) -> 18-25 | F74: Unknown | G74: One year | H74: 37 | I74: =IF(H74="","Unknown",IF(H74<=6,"0-6 months",IF(H74<=12,"7-12 months",IF(H74<=24,"13-24 months",IF(H74<=48,"25-48 months","49+ months"))))) -> 25-48 months | J74: 1099 | K74: 40663 | L74: Fiber | M74: 44809 | N74: No | O74: =IF(N74="Yes",1,IF(N74="No",0,"")) -> 0 | P74: No | Q74: No | R74: No | S74: No | T74: No | U74: =IF(K74="","",K74+ROW()/1000000) -> 40663
A75: C1074 | B75: Kavita Jain | C75: Female | D75: 52 | E75: =IF(D75<=25,"18-25",IF(D75<=35,"26-35",IF(D75<=45,"36-45",IF(D75<=60,"46-60","60+")))) -> 46-60 | F75: Ahmedabad | G75: Month-to-month | H75: 14 | I75: =IF(H75="","Unknown",IF(H75<=6,"0-6 months",IF(H75<=12,"7-12 months",IF(H75<=24,"13-24 months",IF(H75<=48,"25-48 months","49+ months"))))) -> 13-24 months | J75: 1049 | K75: 14686 | L75: Fiber | N75: Yes | O75: =IF(N75="Yes",1,IF(N75="No",0,"")) -> 1 | P75: No | Q75: No | R75: No | S75: No | T75: Date missing | U75: =IF(K75="","",K75+ROW()/1000000) -> 14686
A76: C1075 | B76: Rajesh Bose | C76: Male | D76: 19 | E76: =IF(D76<=25,"18-25",IF(D76<=35,"26-35",IF(D76<=45,"36-45",IF(D76<=60,"46-60","60+")))) -> 18-25 | F76: Kochi | G76: One year | H76: 3 | I76: =IF(H76="","Unknown",IF(H76<=6,"0-6 months",IF(H76<=12,"7-12 months",IF(H76<=24,"13-24 months",IF(H76<=48,"25-48 months","49+ months"))))) -> 0-6 months | J76: 899 | K76: 2697 | L76: DSL | M76: 45818 | N76: No | O76: =IF(N76="Yes",1,IF(N76="No",0,"")) -> 0 | P76: No | Q76: No | R76: No | S76: No | T76: No | U76: =IF(K76="","",K76+ROW()/1000000) -> 2697.0001
A77: C1076 | B77: Kavita Gupta | C77: Female | D77: 55 | E77: =IF(D77<=25,"18-25",IF(D77<=35,"26-35",IF(D77<=45,"36-45",IF(D77<=60,"46-60","60+")))) -> 46-60 | F77: Kolkata | G77: One year | H77: 6 | I77: =IF(H77="","Unknown",IF(H77<=6,"0-6 months",IF(H77<=12,"7-12 months",IF(H77<=24,"13-24 months",IF(H77<=48,"25-48 months","49+ months"))))) -> 0-6 months | J77: 1049 | K77: 6294 | L77: Fiber | M77: 45727 | N77: No | O77: =IF(N77="Yes",1,IF(N77="No",0,"")) -> 0 | P77: No | Q77: No | R77: No | S77: No | T77: No | U77: =IF(K77="","",K77+ROW()/1000000) -> 6294.0001
A78: C1077 | B78: Arjun Joshi | C78: Male | D78: 44 | E78: =IF(D78<=25,"18-25",IF(D78<=35,"26-35",IF(D78<=45,"36-45",IF(D78<=60,"46-60","60+")))) -> 36-45 | F78: Bhopal | G78: Month-to-month | H78: 13 | I78: =IF(H78="","Unknown",IF(H78<=6,"0-6 months",IF(H78<=12,"7-12 months",IF(H78<=24,"13-24 months",IF(H78<=48,"25-48 months","49+ months"))))) -> 13-24 months | J78: 1299 | K78: 16887 | L78: Fiber | M78: 45536 | N78: Yes | O78: =IF(N78="Yes",1,IF(N78="No",0,"")) -> 1 | P78: No | Q78: No | R78: No | S78: No | T78: No | U78: =IF(K78="","",K78+ROW()/1000000) -> 16887
A79: C1078 | B79: Kavita Joshi | C79: Female | D79: 25 | E79: =IF(D79<=25,"18-25",IF(D79<=35,"26-35",IF(D79<=45,"36-45",IF(D79<=60,"46-60","60+")))) -> 18-25 | F79: Kochi | G79: Month-to-month | H79: 1 | I79: =IF(H79="","Unknown",IF(H79<=6,"0-6 months",IF(H79<=12,"7-12 months",IF(H79<=24,"13-24 months",IF(H79<=48,"25-48 months","49+ months"))))) -> 0-6 months | J79: 1299 | K79: 1299 | L79: Fiber | M79: 45897 | N79: Yes | O79: =IF(N79="Yes",1,IF(N79="No",0,"")) -> 1 | P79: No | Q79: No | R79: No | S79: No | T79: No | U79: =IF(K79="","",K79+ROW()/1000000) -> 1299.0001
A80: C1079 | B80: Mohit Patel | C80: Unknown | D80: 57 | E80: =IF(D80<=25,"18-25",IF(D80<=35,"26-35",IF(D80<=45,"36-45",IF(D80<=60,"46-60","60+")))) -> 46-60 | F80: Kochi | G80: Month-to-month | H80: 2 | I80: =IF(H80="","Unknown",IF(H80<=6,"0-6 months",IF(H80<=12,"7-12 months",IF(H80<=24,"13-24 months",IF(H80<=48,"25-48 months","49+ months"))))) -> 0-6 months | J80: 1049 | K80: 2098 | L80: Fiber | M80: 45859 | N80: Yes | O80: =IF(N80="Yes",1,IF(N80="No",0,"")) -> 1 | P80: No | Q80: No | R80: No | S80: No | T80: No | U80: =IF(K80="","",K80+ROW()/1000000) -> 2098.0001
A81: C1080 | B81: Komal Reddy | C81: Female | D81: 47 | E81: =IF(D81<=25,"18-25",IF(D81<=35,"26-35",IF(D81<=45,"36-45",IF(D81<=60,"46-60","60+")))) -> 46-60 | F81: Indore | G81: One year | H81: 11 | I81: =IF(H81="","Unknown",IF(H81<=6,"0-6 months",IF(H81<=12,"7-12 months",IF(H81<=24,"13-24 months",IF(H81<=48,"25-48 months","49+ months"))))) -> 7-12 months | J81: 699 | K81: 7689 | L81: DSL | M81: 45596 | N81: No | O81: =IF(N81="Yes",1,IF(N81="No",0,"")) -> 0 | P81: Yes | Q81: No | R81: Yes | S81: No | T81: No | U81: =IF(K81="","",K81+ROW()/1000000) -> 7689.0001
A82: C1081 | B82: Karan Kapoor | C82: Male | D82: 25 | E82: =IF(D82<=25,"18-25",IF(D82<=35,"26-35",IF(D82<=45,"36-45",IF(D82<=60,"46-60","60+")))) -> 18-25 | F82: Indore | G82: Two year | H82: 38 | I82: =IF(H82="","Unknown",IF(H82<=6,"0-6 months",IF(H82<=12,"7-12 months",IF(H82<=24,"13-24 months",IF(H82<=48,"25-48 months","49+ months"))))) -> 25-48 months | J82: 1199 | K82: 45562 | L82: Fiber | M82: 44773 | N82: No | O82: =IF(N82="Yes",1,IF(N82="No",0,"")) -> 0 | P82: No | Q82: No | R82: No | S82: No | T82: No | U82: =IF(K82="","",K82+ROW()/1000000) -> 45562
A83: C1082 | B83: Ritu Kapoor | C83: Unknown | D83: 53 | E83: =IF(D83<=25,"18-25",IF(D83<=35,"26-35",IF(D83<=45,"36-45",IF(D83<=60,"46-60","60+")))) -> 46-60 | F83: Bangalore | G83: Month-to-month | H83: 17 | I83: =IF(H83="","Unknown",IF(H83<=6,"0-6 months",IF(H83<=12,"7-12 months",IF(H83<=24,"13-24 months",IF(H83<=48,"25-48 months","49+ months"))))) -> 13-24 months | J83: 349 | K83: 5933 | L83: No Internet | M83: 45393 | N83: Yes | O83: =IF(N83="Yes",1,IF(N83="No",0,"")) -> 1 | P83: No | Q83: No | R83: No | S83: No | T83: No | U83: =IF(K83="","",K83+ROW()/1000000) -> 5933.0001
A84: C1083 | B84: Swati Jain | C84: Female | D84: 35 | E84: =IF(D84<=25,"18-25",IF(D84<=35,"26-35",IF(D84<=45,"36-45",IF(D84<=60,"46-60","60+")))) -> 26-35 | F84: Chandigarh | G84: Month-to-month | H84: 19 | I84: =IF(H84="","Unknown",IF(H84<=6,"0-6 months",IF(H84<=12,"7-12 months",IF(H84<=24,"13-24 months",IF(H84<=48,"25-48 months","49+ months"))))) -> 13-24 months | J84: 1199 | K84: 22781 | L84: Fiber | M84: 45344 | N84: No | O84: =IF(N84="Yes",1,IF(N84="No",0,"")) -> 0 | P84: No | Q84: No | R84: No | S84: No | T84: No | U84: =IF(K84="","",K84+ROW()/1000000) -> 22781
A85: C1084 | B85: Isha Joshi | C85: Female | D85: 53 | E85: =IF(D85<=25,"18-25",IF(D85<=35,"26-35",IF(D85<=45,"36-45",IF(D85<=60,"46-60","60+")))) -> 46-60 | F85: Kochi | G85: Month-to-month | H85: 11 | I85: =IF(H85="","Unknown",IF(H85<=6,"0-6 months",IF(H85<=12,"7-12 months",IF(H85<=24,"13-24 months",IF(H85<=48,"25-48 months","49+ months"))))) -> 7-12 months | J85: 999 | K85: 10989 | L85: Fiber | M85: 45591 | N85: No | O85: =IF(N85="Yes",1,IF(N85="No",0,"")) -> 0 | P85: No | Q85: No | R85: No | S85: No | T85: No | U85: =IF(K85="","",K85+ROW()/1000000) -> 10989
A86: C1085 | B86: Sneha Joshi | C86: Female | D86: 65 | E86: =IF(D86<=25,"18-25",IF(D86<=35,"26-35",IF(D86<=45,"36-45",IF(D86<=60,"46-60","60+")))) -> 60+ | F86: Ahmedabad | G86: One year | H86: 25 | I86: =IF(H86="","Unknown",IF(H86<=6,"0-6 months",IF(H86<=12,"7-12 months",IF(H86<=24,"13-24 months",IF(H86<=48,"25-48 months","49+ months"))))) -> 25-48 months | J86: 399 | K86: 9975 | L86: No Internet | M86: 45177 | N86: No | O86: =IF(N86="Yes",1,IF(N86="No",0,"")) -> 0 | P86: No | Q86: No | R86: No | S86: No | T86: No | U86: =IF(K86="","",K86+ROW()/1000000) -> 9975.0001
A87: C1086 | B87: Mohit Bose | C87: Male | D87: 39 | E87: =IF(D87<=25,"18-25",IF(D87<=35,"26-35",IF(D87<=45,"36-45",IF(D87<=60,"46-60","60+")))) -> 36-45 | F87: Chandigarh | G87: Month-to-month | H87: 4 | I87: =IF(H87="","Unknown",IF(H87<=6,"0-6 months",IF(H87<=12,"7-12 months",IF(H87<=24,"13-24 months",IF(H87<=48,"25-48 months","49+ months"))))) -> 0-6 months | J87: 349 | K87: 1396 | L87: No Internet | M87: 45795 | N87: No | O87: =IF(N87="Yes",1,IF(N87="No",0,"")) -> 0 | P87: No | Q87: No | R87: No | S87: No | T87: No | U87: =IF(K87="","",K87+ROW()/1000000) -> 1396.0001
A88: C1087 | B88: Unknown | C88: Male | D88: 68 | E88: =IF(D88<=25,"18-25",IF(D88<=35,"26-35",IF(D88<=45,"36-45",IF(D88<=60,"46-60","60+")))) -> 60+ | F88: Chennai | G88: Month-to-month | I88: =IF(H88="","Unknown",IF(H88<=6,"0-6 months",IF(H88<=12,"7-12 months",IF(H88<=24,"13-24 months",IF(H88<=48,"25-48 months","49+ months"))))) -> Unknown | J88: 1299 | L88: Fiber | M88: 45271 | N88: No | O88: =IF(N88="Yes",1,IF(N88="No",0,"")) -> 0 | P88: No | Q88: No | R88: No | S88: No | T88: Total missing; Tenure missing | U88: =IF(K88="","",K88+ROW()/1000000)
A89: C1088 | B89: Swati Chopra | C89: Female | D89: 63 | E89: =IF(D89<=25,"18-25",IF(D89<=35,"26-35",IF(D89<=45,"36-45",IF(D89<=60,"46-60","60+")))) -> 60+ | F89: Kochi | G89: Month-to-month | H89: 20 | I89: =IF(H89="","Unknown",IF(H89<=6,"0-6 months",IF(H89<=12,"7-12 months",IF(H89<=24,"13-24 months",IF(H89<=48,"25-48 months","49+ months"))))) -> 13-24 months | J89: 999 | K89: 19980 | L89: Fiber | M89: 45305 | N89: No | O89: =IF(N89="Yes",1,IF(N89="No",0,"")) -> 0 | P89: No | Q89: No | R89: No | S89: No | T89: No | U89: =IF(K89="","",K89+ROW()/1000000) -> 19980
A90: C1089 | B90: Vivek Reddy | C90: Male | D90: 66 | E90: =IF(D90<=25,"18-25",IF(D90<=35,"26-35",IF(D90<=45,"36-45",IF(D90<=60,"46-60","60+")))) -> 60+ | F90: Indore | G90: One year | H90: 11 | I90: =IF(H90="","Unknown",IF(H90<=6,"0-6 months",IF(H90<=12,"7-12 months",IF(H90<=24,"13-24 months",IF(H90<=48,"25-48 months","49+ months"))))) -> 7-12 months | J90: 849 | K90: 9339 | L90: DSL | M90: 45573 | N90: Yes | O90: =IF(N90="Yes",1,IF(N90="No",0,"")) -> 1 | P90: No | Q90: No | R90: No | S90: No | T90: No | U90: =IF(K90="","",K90+ROW()/1000000) -> 9339.0001
A91: C1090 | B91: Harsh Patel | C91: Male | D91: 47 | E91: =IF(D91<=25,"18-25",IF(D91<=35,"26-35",IF(D91<=45,"36-45",IF(D91<=60,"46-60","60+")))) -> 46-60 | F91: Kolkata | G91: Month-to-month | H91: 19 | I91: =IF(H91="","Unknown",IF(H91<=6,"0-6 months",IF(H91<=12,"7-12 months",IF(H91<=24,"13-24 months",IF(H91<=48,"25-48 months","49+ months"))))) -> 13-24 months | J91: 1299 | K91: 24681 | L91: Fiber | M91: 45356 | N91: Yes | O91: =IF(N91="Yes",1,IF(N91="No",0,"")) -> 1 | P91: Yes | Q91: No | R91: No | S91: No | T91: No | U91: =IF(K91="","",K91+ROW()/1000000) -> 24681
A92: C1091 | B92: Unknown | C92: Female | D92: 33 | E92: =IF(D92<=25,"18-25",IF(D92<=35,"26-35",IF(D92<=45,"36-45",IF(D92<=60,"46-60","60+")))) -> 26-35 | F92: Ahmedabad | G92: Two year | H92: 60 | I92: =IF(H92="","Unknown",IF(H92<=6,"0-6 months",IF(H92<=12,"7-12 months",IF(H92<=24,"13-24 months",IF(H92<=48,"25-48 months","49+ months"))))) -> 49+ months | J92: 849 | K92: 50940 | L92: DSL | M92: 44128 | N92: No | O92: =IF(N92="Yes",1,IF(N92="No",0,"")) -> 0 | P92: No | Q92: No | R92: No | S92: No | T92: No | U92: =IF(K92="","",K92+ROW()/1000000) -> 50940
A93: C1092 | B93: Aditi Saxena | C93: Female | D93: 47 | E93: =IF(D93<=25,"18-25",IF(D93<=35,"26-35",IF(D93<=45,"36-45",IF(D93<=60,"46-60","60+")))) -> 46-60 | F93: Bangalore | G93: Month-to-month | H93: 19 | I93: =IF(H93="","Unknown",IF(H93<=6,"0-6 months",IF(H93<=12,"7-12 months",IF(H93<=24,"13-24 months",IF(H93<=48,"25-48 months","49+ months"))))) -> 13-24 months | J93: 499 | K93: 9481 | L93: No Internet | M93: 45344 | N93: No | O93: =IF(N93="Yes",1,IF(N93="No",0,"")) -> 0 | P93: Yes | Q93: No | R93: No | S93: No | T93: No | U93: =IF(K93="","",K93+ROW()/1000000) -> 9481.0001
A94: C1093 | B94: Unknown | C94: Female | D94: 72 | E94: =IF(D94<=25,"18-25",IF(D94<=35,"26-35",IF(D94<=45,"36-45",IF(D94<=60,"46-60","60+")))) -> 60+ | F94: Ahmedabad | G94: Month-to-month | H94: 12 | I94: =IF(H94="","Unknown",IF(H94<=6,"0-6 months",IF(H94<=12,"7-12 months",IF(H94<=24,"13-24 months",IF(H94<=48,"25-48 months","49+ months"))))) -> 7-12 months | J94: 1049 | K94: 12588 | L94: Fiber | M94: 45542 | N94: Yes | O94: =IF(N94="Yes",1,IF(N94="No",0,"")) -> 1 | P94: No | Q94: Yes | R94: No | S94: No | T94: No | U94: =IF(K94="","",K94+ROW()/1000000) -> 12588
A95: C1094 | B95: Kavita Sharma | C95: Female | D95: 54 | E95: =IF(D95<=25,"18-25",IF(D95<=35,"26-35",IF(D95<=45,"36-45",IF(D95<=60,"46-60","60+")))) -> 46-60 | F95: Chandigarh | G95: One year | H95: 4 | I95: =IF(H95="","Unknown",IF(H95<=6,"0-6 months",IF(H95<=12,"7-12 months",IF(H95<=24,"13-24 months",IF(H95<=48,"25-48 months","49+ months"))))) -> 0-6 months | J95: 1199 | K95: 4796 | L95: Fiber | M95: 45780 | N95: No | O95: =IF(N95="Yes",1,IF(N95="No",0,"")) -> 0 | P95: No | Q95: No | R95: No | S95: No | T95: No | U95: =IF(K95="","",K95+ROW()/1000000) -> 4796.0001
A96: C1095 | B96: Ritu Yadav | C96: Unknown | D96: 69 | E96: =IF(D96<=25,"18-25",IF(D96<=35,"26-35",IF(D96<=45,"36-45",IF(D96<=60,"46-60","60+")))) -> 60+ | F96: Pune | G96: Month-to-month | H96: 9 | I96: =IF(H96="","Unknown",IF(H96<=6,"0-6 months",IF(H96<=12,"7-12 months",IF(H96<=24,"13-24 months",IF(H96<=48,"25-48 months","49+ months"))))) -> 7-12 months | J96: 849 | K96: 7641 | L96: DSL | M96: 45630 | N96: No | O96: =IF(N96="Yes",1,IF(N96="No",0,"")) -> 0 | P96: No | Q96: No | R96: No | S96: No | T96: No | U96: =IF(K96="","",K96+ROW()/1000000) -> 7641.0001
A97: C1096 | B97: Harsh Kapoor | C97: Male | D97: 20 | E97: =IF(D97<=25,"18-25",IF(D97<=35,"26-35",IF(D97<=45,"36-45",IF(D97<=60,"46-60","60+")))) -> 18-25 | F97: Lucknow | G97: Month-to-month | H97: 10 | I97: =IF(H97="","Unknown",IF(H97<=6,"0-6 months",IF(H97<=12,"7-12 months",IF(H97<=24,"13-24 months",IF(H97<=48,"25-48 months","49+ months"))))) -> 7-12 months | J97: 699 | K97: 6990 | L97: DSL | M97: 45624 | N97: Yes | O97: =IF(N97="Yes",1,IF(N97="No",0,"")) -> 1 | P97: No | Q97: No | R97: No | S97: No | T97: No | U97: =IF(K97="","",K97+ROW()/1000000) -> 6990.0001
A98: C1097 | B98: Payal Jain | C98: Female | D98: 35 | E98: =IF(D98<=25,"18-25",IF(D98<=35,"26-35",IF(D98<=45,"36-45",IF(D98<=60,"46-60","60+")))) -> 26-35 | F98: Chandigarh | G98: Month-to-month | H98: 16 | I98: =IF(H98="","Unknown",IF(H98<=6,"0-6 months",IF(H98<=12,"7-12 months",IF(H98<=24,"13-24 months",IF(H98<=48,"25-48 months","49+ months"))))) -> 13-24 months | J98: 449 | K98: 7184 | L98: No Internet | M98: 45434 | N98: No | O98: =IF(N98="Yes",1,IF(N98="No",0,"")) -> 0 | P98: No | Q98: No | R98: No | S98: No | T98: No | U98: =IF(K98="","",K98+ROW()/1000000) -> 7184.0001
A99: C1098 | B99: Rohit Nair | C99: Male | D99: 73 | E99: =IF(D99<=25,"18-25",IF(D99<=35,"26-35",IF(D99<=45,"36-45",IF(D99<=60,"46-60","60+")))) -> 60+ | F99: Indore | G99: One year | H99: 36 | I99: =IF(H99="","Unknown",IF(H99<=6,"0-6 months",IF(H99<=12,"7-12 months",IF(H99<=24,"13-24 months",IF(H99<=48,"25-48 months","49+ months"))))) -> 25-48 months | J99: 499 | K99: 17964 | L99: No Internet | N99: Yes | O99: =IF(N99="Yes",1,IF(N99="No",0,"")) -> 1 | P99: No | Q99: No | R99: No | S99: No | T99: Date missing | U99: =IF(K99="","",K99+ROW()/1000000) -> 17964
A100: C1099 | B100: Ankit Patel | C100: Male | D100: 61 | E100: =IF(D100<=25,"18-25",IF(D100<=35,"26-35",IF(D100<=45,"36-45",IF(D100<=60,"46-60","60+")))) -> 60+ | F100: Bhopal | G100: One year | H100: 24 | I100: =IF(H100="","Unknown",IF(H100<=6,"0-6 months",IF(H100<=12,"7-12 months",IF(H100<=24,"13-24 months",IF(H100<=48,"25-48 months","49+ months"))))) -> 13-24 months | J100: 1199 | K100: 28776 | L100: Fiber | M100: 45189 | N100: No | O100: =IF(N100="Yes",1,IF(N100="No",0,"")) -> 0 | P100: No | Q100: No | R100: No | S100: No | T100: No | U100: =IF(K100="","",K100+ROW()/1000000) -> 28776
A101: C1100 | B101: Riya Nair | C101: Female | D101: 59 | E101: =IF(D101<=25,"18-25",IF(D101<=35,"26-35",IF(D101<=45,"36-45",IF(D101<=60,"46-60","60+")))) -> 46-60 | F101: Mumbai | G101: One year | H101: 20 | I101: =IF(H101="","Unknown",IF(H101<=6,"0-6 months",IF(H101<=12,"7-12 months",IF(H101<=24,"13-24 months",IF(H101<=48,"25-48 months","49+ months"))))) -> 13-24 months | J101: 1099 | K101: 21980 | L101: Fiber | M101: 45327 | N101: Yes | O101: =IF(N101="Yes",1,IF(N101="No",0,"")) -> 1 | P101: No | Q101: No | R101: No | S101: Yes | T101: No | U101: =IF(K101="","",K101+ROW()/1000000) -> 21980
A102: C1101 | B102: Komal Reddy | C102: Female | D102: 24 | E102: =IF(D102<=25,"18-25",IF(D102<=35,"26-35",IF(D102<=45,"36-45",IF(D102<=60,"46-60","60+")))) -> 18-25 | F102: Hyderabad | G102: Two year | H102: 59 | I102: =IF(H102="","Unknown",IF(H102<=6,"0-6 months",IF(H102<=12,"7-12 months",IF(H102<=24,"13-24 months",IF(H102<=48,"25-48 months","49+ months"))))) -> 49+ months | J102: 699 | K102: 41241 | L102: DSL | M102: 44135 | N102: No | O102: =IF(N102="Yes",1,IF(N102="No",0,"")) -> 0 | P102: No | Q102: No | R102: No | S102: No | T102: No | U102: =IF(K102="","",K102+ROW()/1000000) -> 41241
A103: C1102 | B103: Vivek Chopra | C103: Male | D103: 24 | E103: =IF(D103<=25,"18-25",IF(D103<=35,"26-35",IF(D103<=45,"36-45",IF(D103<=60,"46-60","60+")))) -> 18-25 | F103: Chandigarh | G103: Month-to-month | H103: 9 | I103: =IF(H103="","Unknown",IF(H103<=6,"0-6 months",IF(H103<=12,"7-12 months",IF(H103<=24,"13-24 months",IF(H103<=48,"25-48 months","49+ months"))))) -> 7-12 months | J103: 1199 | K103: 10791 | L103: Fiber | M103: 45644 | N103: Yes | O103: =IF(N103="Yes",1,IF(N103="No",0,"")) -> 1 | P103: No | Q103: No | R103: No | S103: No | T103: No | U103: =IF(K103="","",K103+ROW()/1000000) -> 10791
A104: C1103 | B104: Aman Reddy | C104: Male | D104: 61 | E104: =IF(D104<=25,"18-25",IF(D104<=35,"26-35",IF(D104<=45,"36-45",IF(D104<=60,"46-60","60+")))) -> 60+ | F104: Unknown | G104: Month-to-month | H104: 12 | I104: =IF(H104="","Unknown",IF(H104<=6,"0-6 months",IF(H104<=12,"7-12 months",IF(H104<=24,"13-24 months",IF(H104<=48,"25-48 months","49+ months"))))) -> 7-12 months | J104: 449 | K104: 5388 | L104: No Internet | M104: 45565 | N104: Yes | O104: =IF(N104="Yes",1,IF(N104="No",0,"")) -> 1 | P104: No | Q104: No | R104: No | S104: No | T104: No | U104: =IF(K104="","",K104+ROW()/1000000) -> 5388.0001
A105: C1104 | B105: Neha Saxena | C105: Female | D105: 31 | E105: =IF(D105<=25,"18-25",IF(D105<=35,"26-35",IF(D105<=45,"36-45",IF(D105<=60,"46-60","60+")))) -> 26-35 | F105: Indore | G105: One year | H105: 4 | I105: =IF(H105="","Unknown",IF(H105<=6,"0-6 months",IF(H105<=12,"7-12 months",IF(H105<=24,"13-24 months",IF(H105<=48,"25-48 months","49+ months"))))) -> 0-6 months | J105: 399 | K105: 1596 | L105: No Internet | M105: 45783 | N105: No | O105: =IF(N105="Yes",1,IF(N105="No",0,"")) -> 0 | P105: No | Q105: No | R105: No | S105: No | T105: No | U105: =IF(K105="","",K105+ROW()/1000000) -> 1596.0001
A106: C1105 | B106: Vikram Mishra | C106: Male | D106: 47 | E106: =IF(D106<=25,"18-25",IF(D106<=35,"26-35",IF(D106<=45,"36-45",IF(D106<=60,"46-60","60+")))) -> 46-60 | F106: Lucknow | G106: Month-to-month | H106: 11 | I106: =IF(H106="","Unknown",IF(H106<=6,"0-6 months",IF(H106<=12,"7-12 months",IF(H106<=24,"13-24 months",IF(H106<=48,"25-48 months","49+ months"))))) -> 7-12 months | J106: 549 | K106: 6039 | L106: Unknown | M106: 45571 | N106: Yes | O106: =IF(N106="Yes",1,IF(N106="No",0,"")) -> 1 | P106: Yes | Q106: No | R106: No | S106: No | T106: No | U106: =IF(K106="","",K106+ROW()/1000000) -> 6039.0001
A107: C1106 | B107: Rohit Mishra | C107: Male | D107: 34 | E107: =IF(D107<=25,"18-25",IF(D107<=35,"26-35",IF(D107<=45,"36-45",IF(D107<=60,"46-60","60+")))) -> 26-35 | F107: Kochi | G107: Month-to-month | H107: 1 | I107: =IF(H107="","Unknown",IF(H107<=6,"0-6 months",IF(H107<=12,"7-12 months",IF(H107<=24,"13-24 months",IF(H107<=48,"25-48 months","49+ months"))))) -> 0-6 months | J107: 899 | K107: 899 | L107: Fiber | M107: 45891 | N107: No | O107: =IF(N107="Yes",1,IF(N107="No",0,"")) -> 0 | P107: No | Q107: No | R107: No | S107: No | T107: No | U107: =IF(K107="","",K107+ROW()/1000000) -> 899.00011
A108: C1107 | B108: Priya Gupta | C108: Female | D108: 34 | E108: =IF(D108<=25,"18-25",IF(D108<=35,"26-35",IF(D108<=45,"36-45",IF(D108<=60,"46-60","60+")))) -> 26-35 | F108: Delhi | G108: Month-to-month | H108: 4 | I108: =IF(H108="","Unknown",IF(H108<=6,"0-6 months",IF(H108<=12,"7-12 months",IF(H108<=24,"13-24 months",IF(H108<=48,"25-48 months","49+ months"))))) -> 0-6 months | J108: 899 | K108: 3596 | L108: Fiber | M108: 45797 | N108: Yes | O108: =IF(N108="Yes",1,IF(N108="No",0,"")) -> 1 | P108: No | Q108: No | R108: No | S108: No | T108: No | U108: =IF(K108="","",K108+ROW()/1000000) -> 3596.0001
A109: C1108 | B109: Ankit Jain | C109: Male | D109: 32 | E109: =IF(D109<=25,"18-25",IF(D109<=35,"26-35",IF(D109<=45,"36-45",IF(D109<=60,"46-60","60+")))) -> 26-35 | F109: Lucknow | G109: Month-to-month | H109: 22 | I109: =IF(H109="","Unknown",IF(H109<=6,"0-6 months",IF(H109<=12,"7-12 months",IF(H109<=24,"13-24 months",IF(H109<=48,"25-48 months","49+ months"))))) -> 13-24 months | J109: 1049 | K109: 23078 | L109: Fiber | M109: 45268 | N109: No | O109: =IF(N109="Yes",1,IF(N109="No",0,"")) -> 0 | P109: No | Q109: No | R109: No | S109: No | T109: No | U109: =IF(K109="","",K109+ROW()/1000000) -> 23078
A110: C1109 | B110: Gaurav Rao | C110: Male | D110: 45 | E110: =IF(D110<=25,"18-25",IF(D110<=35,"26-35",IF(D110<=45,"36-45",IF(D110<=60,"46-60","60+")))) -> 36-45 | F110: Indore | G110: Month-to-month | H110: 15 | I110: =IF(H110="","Unknown",IF(H110<=6,"0-6 months",IF(H110<=12,"7-12 months",IF(H110<=24,"13-24 months",IF(H110<=48,"25-48 months","49+ months"))))) -> 13-24 months | J110: 899 | K110: 13485 | L110: Fiber | M110: 45476 | N110: No | O110: =IF(N110="Yes",1,IF(N110="No",0,"")) -> 0 | P110: No | Q110: No | R110: No | S110: No | T110: No | U110: =IF(K110="","",K110+ROW()/1000000) -> 13485
A111: C1110 | B111: Suresh Yadav | C111: Male | D111: 58 | E111: =IF(D111<=25,"18-25",IF(D111<=35,"26-35",IF(D111<=45,"36-45",IF(D111<=60,"46-60","60+")))) -> 46-60 | F111: Lucknow | G111: Month-to-month | H111: 20 | I111: =IF(H111="","Unknown",IF(H111<=6,"0-6 months",IF(H111<=12,"7-12 months",IF(H111<=24,"13-24 months",IF(H111<=48,"25-48 months","49+ months"))))) -> 13-24 months | J111: 799 | K111: 15980 | L111: DSL | M111: 45315 | N111: No | O111: =IF(N111="Yes",1,IF(N111="No",0,"")) -> 0 | P111: No | Q111: No | R111: No | S111: No | T111: No | U111: =IF(K111="","",K111+ROW()/1000000) -> 15980
... A152: C1151 | B152: Kavita Verma | C152: Female | D152: 66 | E152: =IF(D152<=25,"18-25",IF(D152<=35,"26-35",IF(D152<=45,"36-45",IF(D152<=60,"46-60","60+")))) -> 60+ | F152: Indore | G152: Unknown | H152: 2 | I152: =IF(H152="","Unknown",IF(H152<=6,"0-6 months",IF(H152<=12,"7-12 months",IF(H152<=24,"13-24 months",IF(H152<=48,"25-48 months","49+ months"))))) -> 0-6 months | J152: 1199 | K152: 2398 | L152: Fiber | M152: 45843 | N152: Yes | O152: =IF(N152="Yes",1,IF(N152="No",0,"")) -> 1 | P152: No | Q152: No | R152: No | S152: No | T152: No | U152: =IF(K152="","",K152+ROW()/1000000) -> 2398.0002
A153: C1152 | B153: Nisha Rao | C153: Female | D153: 65 | E153: =IF(D153<=25,"18-25",IF(D153<=35,"26-35",IF(D153<=45,"36-45",IF(D153<=60,"46-60","60+")))) -> 60+ | F153: Ahmedabad | G153: Two year | H153: 24 | I153: =IF(H153="","Unknown",IF(H153<=6,"0-6 months",IF(H153<=12,"7-12 months",IF(H153<=24,"13-24 months",IF(H153<=48,"25-48 months","49+ months"))))) -> 13-24 months | J153: 1199 | K153: 28776 | L153: Fiber | N153: No | O153: =IF(N153="Yes",1,IF(N153="No",0,"")) -> 0 | P153: No | Q153: Yes | R153: No | S153: No | T153: Date missing | U153: =IF(K153="","",K153+ROW()/1000000) -> 28776
...

Sheet analysis 
A1: Age group | B1: yes | C1: no | D1: churn rate | AE1: Monthly revenue lost | AF1: Formula
A2: 18-25 | B2: =COUNTIFS(Customer_churn_data!$E$2:$E$2001,$A2,Customer_churn_data!$N$2:$N$2001,"Yes") -> 85 | C2: =COUNTIFS(Customer_churn_data!$E$2:$E$2001,$A2,Customer_churn_data!$N$2:$N$2001,"No") -> 172 | D2: =B2/(B2+C2) -> 0.3307393 | F2: level 1: | H2: Here is an example for Q2 and Q5, in your own words:
A3: 26-35 | B3: =COUNTIFS(Customer_churn_data!$E$2:$E$2001,$A3,Customer_churn_data!$N$2:$N$2001,"Yes") -> 100 | C3: =COUNTIFS(Customer_churn_data!$E$2:$E$2001,$A3,Customer_churn_data!$N$2:$N$2001,"No") -> 230 | D3: =B3/(B3+C3) -> 0.3030303 | H3: "One in three customers is leaving, which is very high. Most of the churn (78%) comes from Month-to-month contracts, so the retention effort should target them first."
A4: 36-45 | B4: =COUNTIFS(Customer_churn_data!$E$2:$E$2001,$A4,Customer_churn_data!$N$2:$N$2001,"Yes") -> 121 | C4: =COUNTIFS(Customer_churn_data!$E$2:$E$2001,$A4,Customer_churn_data!$N$2:$N$2001,"No") -> 204 | D4: =B4/(B4+C4) -> 0.37230769 | G4: 1. How many unique customers are in the dataset?
A5: 46-60 | B5: =COUNTIFS(Customer_churn_data!$E$2:$E$2001,$A5,Customer_churn_data!$N$2:$N$2001,"Yes") -> 188 | C5: =COUNTIFS(Customer_churn_data!$E$2:$E$2001,$A5,Customer_churn_data!$N$2:$N$2001,"No") -> 379 | D5: =B5/(B5+C5) -> 0.33156966 | G5: 2. How many customers have churned, and what is the overall churn rate (%)? Exclude customers whose churn status is "Unknown" from the calculation.
A6: 60+ | B6: =COUNTIFS(Customer_churn_data!$E$2:$E$2001,$A6,Customer_churn_data!$N$2:$N$2001,"Yes") -> 171 | C6: =COUNTIFS(Customer_churn_data!$E$2:$E$2001,$A6,Customer_churn_data!$N$2:$N$2001,"No") -> 315 | D6: =B6/(B6+C6) -> 0.35185185 | G6: 3. What is the average Monthly Charges across all customers?
G7: 4. What is the total revenue (sum of Total Charges) across all customers?
G8: 5. How many customers are on a Month-to-month contract and have churned?
K10: insight:
F11: solutions : | H11: 1 | I11: =COUNTA(Customer_churn_data!$A$2:$A$2001) -> 2000 | K11: Insight: "The cleaned base has 2,000 unique customers, after removing 50 duplicates and 8 blank rows."
H12: 2 | I12: =COUNTIF(Customer_churn_data!$N$2:$N$2001,"Yes") -> 665 | J12: =COUNTIF(Customer_churn_data!$N$2:$N$2001,"Yes")/(COUNTIF(Customer_churn_data!$N$2:$N$2001,"Yes")+COUNTIF(Customer_churn_data!$N$2:$N$2001,"No")) -> 0.33842239 | K12: Insight: "One in three customers has left. That is very high and needs urgent action."
H13: 3 | I13: =AVERAGE(Customer_churn_data!$J$2:$J$2001) -> 847.00404 | K13: Insight: "The average customer pays about ₹847 a month. This is the baseline to price retention offers against."
H14: 4 | I14: =SUM(Customer_churn_data!$K$2:$K$2001) -> 32017927 | K14: . Insight: "About ₹3.2 crore of lifetime billing sits in this customer base, so losing a third of customers is a serious revenue risk." Note: 17 Total Charges cells are blank, so the real figure is slightly higher.
H15: 5 | I15: =COUNTIFS(Customer_churn_data!$G$2:$G$2001,"Month-to-month",Customer_churn_data!$N$2:$N$2001,"Yes") -> 516 | K15: Insight: "516 of 665 churned customers (78%) were on Month-to-month plans, so contract type is the main churn driver."
F17: level 2: | G17: pivot tables
G18: 6. What is the churn rate for each Contract Type? Which contract is the riskiest? (You've already done this one ✅)
G19: 7. What is the churn rate for each Internet Service type (DSL, Fiber, No Internet)? Which service has the highest churn?
G20: 8. City-wise analysis: For each city, show the number of customers, total revenue (Total Charges) and churn rate. Which are the top 3 and bottom 3 cities by churn rate?
G21: 9. Tenure buckets: Create buckets (0-6, 7-12, 13-24, 25-48, 49+ months). Which bucket has the highest churn rate?
G22: 10. Age groups: Create groups (18-25, 26-35, 36-45, 46-60, 60+). Which age group churns the most?
F24: level 3:
G26: Q11. Monthly revenue lost from churned customers
G27: Q12. Annual revenue at risk
G28: Q13. Retention scenario (reduce Month-to-month churn by 10 points)
G29: Q14. Top 10 customers by Total Charges
G30: Q15. Customer lookup box
G31: Q16. City churn rate table with population
L33: insights:
F34: solutions:
G35: 11 | H35: =SUMIFS(Customer_churn_data!$J$2:$J$2001,Customer_churn_data!$N$2:$N$2001,"Yes") -> 567095 | L35: Insight: "Churned customers represented about 34% of total monthly billing. Almost a third of recurring revenue has walked out." Note: 10 churned customers have a blank Monthly Charge, so this is slightly understated.
G36: 12 | H36: monthly revenue at risk | J36: =SUMIFS(Customer_churn_data!$J$2:$J$2001,Customer_churn_data!$N$2:$N$2001,"Yes") -> 567095 | L36: Insight: About a third of the company's monthly billing is lost to churn, so even a small improvement in retention is worth lakhs.
H37: annual revenue at risk | J37: =J36*12 -> 6805140
G38: 13 | H38: churn reduction (assumption) | J38: 0.1 | O38: Insight: "Cutting Month-to-month churn from 47.8% to 37.8% would save about 108 customers and around ₹11 lakh a year. Month-to-month customers also account for about 77% of the monthly revenue lost, so this is the best place to spend retention budget." Change B1 to 5% or 15% and the answer updates automatically, which is a good thing to show in an interview.
H39: moth to month customers with known churn status | M39: =COUNTIFS(Customer_churn_data!$G$2:$G$2001,"Month-to-month",Customer_churn_data!$N$2:$N$2001,"Yes")+COUNTIFS(Customer_churn_data!$G$2:$G$2001,"Month-to-month",Customer_churn_data!$N$2:$N$2001,"No") -> 1080
H40: avg monthly charge of churned month to month | M40: =AVERAGEIFS(Customer_churn_data!$J$2:$J$2001,Customer_churn_data!$G$2:$G$2001,"Month-to-month",Customer_churn_data!$N$2:$N$2001,"Yes") -> 857.85827
H41: Customer saved | I41: 108
H42: Monthly revenue saved | I42: =M39*M40 -> 926486.93
B43: 14. solution-> | H43: Annual revenue saved | I43: =I42*12 -> 11117843
B44: rank | C44: Totalkey | D44: CustID | E44: Total Charges | F44: Churn
B45: 1 | C45: =LARGE(Customer_churn_data!$U$2:$U$2001,B45) -> 89631.001 | D45: =INDEX(Customer_churn_data!$A$2:$A$2001,MATCH(C45,Customer_churn_data!$U$2:$U$2001,0)) -> C1528 | E45: =INDEX(Customer_churn_data!$K$2:$K$2001,MATCH(C45,Customer_churn_data!$U$2:$U$2001,0)) -> 89631 | F45: =INDEX(Customer_churn_data!$N$2:$N$2001,MATCH(C45,Customer_churn_data!$U$2:$U$2001,0)) -> No
B46: 2 | C46: =LARGE(Customer_churn_data!$U$2:$U$2001,B46) -> 89631 | D46: =INDEX(Customer_churn_data!$A$2:$A$2001,MATCH(C46,Customer_churn_data!$U$2:$U$2001,0)) -> C1315 | E46: =INDEX(Customer_churn_data!$K$2:$K$2001,MATCH(C46,Customer_churn_data!$U$2:$U$2001,0)) -> 89631 | F46: =INDEX(Customer_churn_data!$N$2:$N$2001,MATCH(C46,Customer_churn_data!$U$2:$U$2001,0)) -> No | H46: Insight: "All top 10 customers are on Two-year contracts, and 8 of 10 are still active. The 2 who churned (C1023, C2457) are each worth over ₹80,000 and should get a personal win-back call."
B47: 3 | C47: =LARGE(Customer_churn_data!$U$2:$U$2001,B47) -> 87033.001 | D47: =INDEX(Customer_churn_data!$A$2:$A$2001,MATCH(C47,Customer_churn_data!$U$2:$U$2001,0)) -> C2404 | E47: =INDEX(Customer_churn_data!$K$2:$K$2001,MATCH(C47,Customer_churn_data!$U$2:$U$2001,0)) -> 87033 | F47: =INDEX(Customer_churn_data!$N$2:$N$2001,MATCH(C47,Customer_churn_data!$U$2:$U$2001,0)) -> No | G47: 15. solution-
B48: 4 | C48: =LARGE(Customer_churn_data!$U$2:$U$2001,B48) -> 86328 | D48: =INDEX(Customer_churn_data!$A$2:$A$2001,MATCH(C48,Customer_churn_data!$U$2:$U$2001,0)) -> C1007 | E48: =INDEX(Customer_churn_data!$K$2:$K$2001,MATCH(C48,Customer_churn_data!$U$2:$U$2001,0)) -> 86328 | F48: =INDEX(Customer_churn_data!$N$2:$N$2001,MATCH(C48,Customer_churn_data!$U$2:$U$2001,0)) -> No | G48: CustID | H48: C1050
B49: 5 | C49: =LARGE(Customer_churn_data!$U$2:$U$2001,B49) -> 83930 | D49: =INDEX(Customer_churn_data!$A$2:$A$2001,MATCH(C49,Customer_churn_data!$U$2:$U$2001,0)) -> C1023 | E49: =INDEX(Customer_churn_data!$K$2:$K$2001,MATCH(C49,Customer_churn_data!$U$2:$U$2001,0)) -> 83930 | F49: =INDEX(Customer_churn_data!$N$2:$N$2001,MATCH(C49,Customer_churn_data!$U$2:$U$2001,0)) -> Yes | G49: Name | H49: =IFERROR(INDEX(Customer_churn_data!$B$2:$B$2001,MATCH($H$48,Customer_churn_data!$A$2:$A$2001,0)),"Not found") -> Nisha Mishra
B50: 6 | C50: =LARGE(Customer_churn_data!$U$2:$U$2001,B50) -> 82731.002 | D50: =INDEX(Customer_churn_data!$A$2:$A$2001,MATCH(C50,Customer_churn_data!$U$2:$U$2001,0)) -> C2645 | E50: =INDEX(Customer_churn_data!$K$2:$K$2001,MATCH(C50,Customer_churn_data!$U$2:$U$2001,0)) -> 82731 | F50: =INDEX(Customer_churn_data!$N$2:$N$2001,MATCH(C50,Customer_churn_data!$U$2:$U$2001,0)) -> No | G50: City | H50: =IFERROR(INDEX(Customer_churn_data!$F$2:$F$2001,MATCH($H$48,Customer_churn_data!$A$2:$A$2001,0)),"Not found") -> Bhopal
B51: 7 | C51: =LARGE(Customer_churn_data!$U$2:$U$2001,B51) -> 82731 | D51: =INDEX(Customer_churn_data!$A$2:$A$2001,MATCH(C51,Customer_churn_data!$U$2:$U$2001,0)) -> C1381 | E51: =INDEX(Customer_churn_data!$K$2:$K$2001,MATCH(C51,Customer_churn_data!$U$2:$U$2001,0)) -> 82731 | F51: =INDEX(Customer_churn_data!$N$2:$N$2001,MATCH(C51,Customer_churn_data!$U$2:$U$2001,0)) -> No | G51: Monthly Charges | H51: =IFERROR(INDEX(Customer_churn_data!$J$2:$J$2001,MATCH($H$48,Customer_churn_data!$A$2:$A$2001,0)),"Not found") -> 999 | I51: insight: "The lookup box lets a support or retention agent type any CustID and instantly see the customer's name, city, monthly bill and churn status. Instead of searching through 2,000 rows, the agent gets the answer in seconds, which makes win-back calls and complaint handling faster and less error-prone."
B52: 8 | C52: =LARGE(Customer_churn_data!$U$2:$U$2001,B52) -> 81532 | D52: =INDEX(Customer_churn_data!$A$2:$A$2001,MATCH(C52,Customer_churn_data!$U$2:$U$2001,0)) -> C1463 | E52: =INDEX(Customer_churn_data!$K$2:$K$2001,MATCH(C52,Customer_churn_data!$U$2:$U$2001,0)) -> 81532 | F52: =INDEX(Customer_churn_data!$N$2:$N$2001,MATCH(C52,Customer_churn_data!$U$2:$U$2001,0)) -> No | G52: Churn | H52: =IFERROR(INDEX(Customer_churn_data!$N$2:$N$2001,MATCH($H$48,Customer_churn_data!$A$2:$A$2001,0)),"Not found") -> Yes | I52: Because analysis is only useful if the business can act on it. This turns the dataset into a simple tool a non-technical team can use without touching formulas."
B53: 9 | C53: =LARGE(Customer_churn_data!$U$2:$U$2001,B53) -> 80430.001 | D53: =INDEX(Customer_churn_data!$A$2:$A$2001,MATCH(C53,Customer_churn_data!$U$2:$U$2001,0)) -> C2457 | E53: =INDEX(Customer_churn_data!$K$2:$K$2001,MATCH(C53,Customer_churn_data!$U$2:$U$2001,0)) -> 80430 | F53: =INDEX(Customer_churn_data!$N$2:$N$2001,MATCH(C53,Customer_churn_data!$U$2:$U$2001,0)) -> Yes
B54: 10 | C54: =LARGE(Customer_churn_data!$U$2:$U$2001,B54) -> 79239.002 | D54: =INDEX(Customer_churn_data!$A$2:$A$2001,MATCH(C54,Customer_churn_data!$U$2:$U$2001,0)) -> C2898 | E54: =INDEX(Customer_churn_data!$K$2:$K$2001,MATCH(C54,Customer_churn_data!$U$2:$U$2001,0)) -> 79239 | F54: =INDEX(Customer_churn_data!$N$2:$N$2001,MATCH(C54,Customer_churn_data!$U$2:$U$2001,0)) -> No | G54: 16. solution-
G55: city | H55: customers | I55: yes | J55: no | K55: churn rate
G56: Ahmedabad | H56: =COUNTIF(Customer_churn_data!$F$2:$F$2001,$G56) -> 147 | I56: =COUNTIFS(Customer_churn_data!$F$2:$F$2001,$G56,Customer_churn_data!$N$2:$N$2001,"Yes") -> 43 | J56: =COUNTIFS(Customer_churn_data!$F$2:$F$2001,$G56,Customer_churn_data!$N$2:$N$2001,"No") -> 103 | K56: =I56/(I56+J56) -> 0.29452055
G57: Bangalore | H57: =COUNTIF(Customer_churn_data!$F$2:$F$2001,$G57) -> 143 | I57: =COUNTIFS(Customer_churn_data!$F$2:$F$2001,$G57,Customer_churn_data!$N$2:$N$2001,"Yes") -> 41 | J57: =COUNTIFS(Customer_churn_data!$F$2:$F$2001,$G57,Customer_churn_data!$N$2:$N$2001,"No") -> 99 | K57: =I57/(I57+J57) -> 0.29285714 | M57: "I used the lookup box to turn the table into a quick tool: type any city, get its customer count and churn rate instantly."
G58: Bhopal | H58: =COUNTIF(Customer_churn_data!$F$2:$F$2001,$G58) -> 123 | I58: =COUNTIFS(Customer_churn_data!$F$2:$F$2001,$G58,Customer_churn_data!$N$2:$N$2001,"Yes") -> 42 | J58: =COUNTIFS(Customer_churn_data!$F$2:$F$2001,$G58,Customer_churn_data!$N$2:$N$2001,"No") -> 81 | K58: =I58/(I58+J58) -> 0.34146341
G59: Chandigarh | H59: =COUNTIF(Customer_churn_data!$F$2:$F$2001,$G59) -> 139 | I59: =COUNTIFS(Customer_churn_data!$F$2:$F$2001,$G59,Customer_churn_data!$N$2:$N$2001,"Yes") -> 50 | J59: =COUNTIFS(Customer_churn_data!$F$2:$F$2001,$G59,Customer_churn_data!$N$2:$N$2001,"No") -> 87 | K59: =I59/(I59+J59) -> 0.3649635 | L59: insight: | M59: "Churn ranges from 28.8% in Kolkata to 38.1% in Chennai, a gap of about 9 points. The three highest-churn cities are Chennai (38.1%), Indore (37.2%) and Chandigarh (36.5%), while Kolkata, Bangalore and Ahmedabad retain best. However, every city has only about 120 to 155 customers, so part of this gap may be random variation rather than a real local problem. City is a weaker churn driver than contract type (47.8% vs 10.9%) or tenure (49.7% for the first 6 months vs 8.6% after 4 years). The business should first fix contract and tenure issues everywhere, and only then investigate Chennai, Indore and Chandigarh for local causes such as network quality or competitor offers."
G60: Chennai | H60: =COUNTIF(Customer_churn_data!$F$2:$F$2001,$G60) -> 129 | I60: =COUNTIFS(Customer_churn_data!$F$2:$F$2001,$G60,Customer_churn_data!$N$2:$N$2001,"Yes") -> 48 | J60: =COUNTIFS(Customer_churn_data!$F$2:$F$2001,$G60,Customer_churn_data!$N$2:$N$2001,"No") -> 78 | K60: =I60/(I60+J60) -> 0.38095238
G61: Delhi | H61: =COUNTIF(Customer_churn_data!$F$2:$F$2001,$G61) -> 149 | I61: =COUNTIFS(Customer_churn_data!$F$2:$F$2001,$G61,Customer_churn_data!$N$2:$N$2001,"Yes") -> 51 | J61: =COUNTIFS(Customer_churn_data!$F$2:$F$2001,$G61,Customer_churn_data!$N$2:$N$2001,"No") -> 93 | K61: =I61/(I61+J61) -> 0.35416667
G62: Hyderabad | H62: =COUNTIF(Customer_churn_data!$F$2:$F$2001,$G62) -> 136 | I62: =COUNTIFS(Customer_churn_data!$F$2:$F$2001,$G62,Customer_churn_data!$N$2:$N$2001,"Yes") -> 46 | J62: =COUNTIFS(Customer_churn_data!$F$2:$F$2001,$G62,Customer_churn_data!$N$2:$N$2001,"No") -> 88 | K62: =I62/(I62+J62) -> 0.34328358
G63: Indore | H63: =COUNTIF(Customer_churn_data!$F$2:$F$2001,$G63) -> 138 | I63: =COUNTIFS(Customer_churn_data!$F$2:$F$2001,$G63,Customer_churn_data!$N$2:$N$2001,"Yes") -> 51 | J63: =COUNTIFS(Customer_churn_data!$F$2:$F$2001,$G63,Customer_churn_data!$N$2:$N$2001,"No") -> 86 | K63: =I63/(I63+J63) -> 0.37226277
G64: Jaipur | H64: =COUNTIF(Customer_churn_data!$F$2:$F$2001,$G64) -> 141 | I64: =COUNTIFS(Customer_churn_data!$F$2:$F$2001,$G64,Customer_churn_data!$N$2:$N$2001,"Yes") -> 48 | J64: =COUNTIFS(Customer_churn_data!$F$2:$F$2001,$G64,Customer_churn_data!$N$2:$N$2001,"No") -> 90 | K64: =I64/(I64+J64) -> 0.34782609
G65: Kochi | H65: =COUNTIF(Customer_churn_data!$F$2:$F$2001,$G65) -> 154 | I65: =COUNTIFS(Customer_churn_data!$F$2:$F$2001,$G65,Customer_churn_data!$N$2:$N$2001,"Yes") -> 51 | J65: =COUNTIFS(Customer_churn_data!$F$2:$F$2001,$G65,Customer_churn_data!$N$2:$N$2001,"No") -> 98 | K65: =I65/(I65+J65) -> 0.34228188
G66: Kolkata | H66: =COUNTIF(Customer_churn_data!$F$2:$F$2001,$G66) -> 139 | I66: =COUNTIFS(Customer_churn_data!$F$2:$F$2001,$G66,Customer_churn_data!$N$2:$N$2001,"Yes") -> 40 | J66: =COUNTIFS(Customer_churn_data!$F$2:$F$2001,$G66,Customer_churn_data!$N$2:$N$2001,"No") -> 99 | K66: =I66/(I66+J66) -> 0.28776978
G67: Lucknow | H67: =COUNTIF(Customer_churn_data!$F$2:$F$2001,$G67) -> 143 | I67: =COUNTIFS(Customer_churn_data!$F$2:$F$2001,$G67,Customer_churn_data!$N$2:$N$2001,"Yes") -> 50 | J67: =COUNTIFS(Customer_churn_data!$F$2:$F$2001,$G67,Customer_churn_data!$N$2:$N$2001,"No") -> 91 | K67: =I67/(I67+J67) -> 0.35460993
G68: Mumbai | H68: =COUNTIF(Customer_churn_data!$F$2:$F$2001,$G68) -> 133 | I68: =COUNTIFS(Customer_churn_data!$F$2:$F$2001,$G68,Customer_churn_data!$N$2:$N$2001,"Yes") -> 47 | J68: =COUNTIFS(Customer_churn_data!$F$2:$F$2001,$G68,Customer_churn_data!$N$2:$N$2001,"No") -> 82 | K68: =I68/(I68+J68) -> 0.36434109
G69: Pune | H69: =COUNTIF(Customer_churn_data!$F$2:$F$2001,$G69) -> 141 | I69: =COUNTIFS(Customer_churn_data!$F$2:$F$2001,$G69,Customer_churn_data!$N$2:$N$2001,"Yes") -> 44 | J69: =COUNTIFS(Customer_churn_data!$F$2:$F$2001,$G69,Customer_churn_data!$N$2:$N$2001,"No") -> 96 | K69: =I69/(I69+J69) -> 0.31428571

Sheet Pivot tables 
A2: Row Labels | B2: Count of CustID
A3: Month-to-month | B3: 1097
A4: One year | B4: 501
A5: Two year | B5: 375
A6: Unknown | B6: 27
A7: (blank)
A8: Grand Total | B8: 2000
A18: 6. Insight: Month-to-month customers churn more than 4x as often as two-year customers. Contract length is the strongest churn driver in this data.
A19: Action: Offer discounts or perks to move month-to-month customers onto one-year plans.
A21: Count of CustID | B21: Column Labels
A22: Row Labels | B22: No | C22: Unknown | D22: Yes | E22: Grand Total
A23: DSL | B23: 488 | C23: 13 | D23: 196 | E23: 697
A24: Fiber | B24: 541 | C24: 16 | D24: 328 | E24: 885
A25: No Internet | B25: 240 | C25: 6 | D25: 130 | E25: 376
A26: Unknown | B26: 31 | D26: 11 | E26: 42
A27: Grand Total | B27: 1300 | C27: 35 | D27: 665 | E27: 2000
A28: 7. Insight: Fiber customers pay the most but churn the most, about 9 points above DSL. That is the costliest kind of churn. The "No Internet" group also churns at a high rate, which suggests those customers get little value from the plan.
A29: Action: Investigate Fiber service quality and pricing. Consider bundling offers for No Internet customers.
A31: Row Labels | B31: Count of CustID
A32: Ahmedabad | B32: 147
A33: Bangalore | B33: 143
A34: Bhopal | B34: 123
A35: Chandigarh | B35: 139
A36: Chennai | B36: 129
A37: Delhi | B37: 149
A38: Hyderabad | B38: 136
A39: Indore | B39: 138
A40: Jaipur | B40: 141
A41: Kochi | B41: 154
A42: Kolkata | B42: 139
A43: Lucknow | B43: 143
... A47: Grand Total | B47: 2000
A48: 8. Insight: City matters much less than contract type. The gap between best and worst city is about 9 points, and each city has only about 125 to 150 customers, so part of that gap is likely random variation.
A49: Action: Don't launch city-specific campaigns based on this alone. Use contract and tenure to target customers instead, and treat city as a secondary filter. Revenue per city is fairly even (₹19 to 25 lakh), so no single city dominates.
A51: Count of CustID | B51: Column Labels
A52: Row Labels | B52: No | C52: Unknown | D52: Yes | E52: Grand Total
A53: DSL | B53: 0.70014347 | C53: 0.018651363 | D53: 0.28120516 | E53: 1
A54: Fiber | B54: 0.61129944 | C54: 0.018079096 | D54: 0.37062147 | E54: 1
A55: No Internet | B55: 0.63829787 | C55: 0.015957447 | D55: 0.34574468 | E55: 1
A56: Unknown | B56: 0.73809524 | C56: 0 | D56: 0.26190476 | E56: 1
A57: Grand Total | B57: 0.65 | C57: 0.0175 | D57: 0.3325 | E57: 1
A58: 9. Buisness insight :
A59: "Fiber is the most expensive service and also loses the most customers. Service quality and pricing of Fiber should be investigated first."
A61: Row Labels | B61: Count of CustID | C61: Average of Churn_Flag
A62: 0-6 months | B62: 393 | C62: 0.49226804
A63: 13-24 months | B63: 756 | C63: 0.34986595
A64: 25-48 months | B64: 297 | C64: 0.16551724
A65: 49+ months | B65: 142 | C65: 0.085714286
A66: 7-12 months | B66: 412 | C66: 0.38154613
A67: Grand Total | B67: 2000 | C67: 0.33842239
A70: 10. Insight: "Nearly half of new customers leave within 6 months, and churn keeps falling as tenure increases. Onboarding and early retention are the biggest opportunity."
A81: Row Labels | B81: Count of CustID | C81: Sum of Total Charges (₹) | D81: Average of Churn_Flag
A82: Ahmedabad | B82: 147 | C82: 2445230 | D82: 0.29452055
A83: Bangalore | B83: 143 | C83: 2407088 | D83: 0.29285714
A84: Bhopal | B84: 123 | C84: 1863943 | D84: 0.34146341
A85: Chandigarh | B85: 139 | C85: 2024423 | D85: 0.3649635
A86: Chennai | B86: 129 | C86: 1993418 | D86: 0.38095238
A87: Delhi | B87: 149 | C87: 2273932 | D87: 0.35416667
A88: Hyderabad | B88: 136 | C88: 2153373 | D88: 0.34328358
A89: Indore | B89: 138 | C89: 2252899 | D89: 0.37226277
A90: Jaipur | B90: 141 | C90: 2388960 | D90: 0.34782609
A91: Kochi | B91: 154 | C91: 2361669 | D91: 0.34228188
A92: Kolkata | B92: 139 | C92: 2191210 | D92: 0.28776978
A93: Lucknow | B93: 143 | C93: 2134079 | D93: 0.35460993
... A97: Grand Total | B97: 2000 | C97: 32017927 | D97: 0.33842239
B99: Insight: "City differences are small (about 9 points) and each city has only about 130 to 150 customers, so city is a weaker churn driver than contract type or tenure."
A101: Row Labels | B101: Count of CustID | C101: Average of Churn_Flag
A102: 18-25 | B102: 259 | C102: 0.3307393
A103: 26-35 | B103: 338 | C103: 0.3030303
A104: 36-45 | B104: 329 | C104: 0.37230769
A105: 46-60 | B105: 577 | C105: 0.33156966
A106: 60+ | B106: 497 | C106: 0.35185185
A107: Grand Total | B107: 2000 | C107: 0.33842239
A109: Insight: "Age has only a weak link to churn. Rates range from 30% to 37% with no clear pattern, so age-based targeting is not worth it."

Sheet dashboard
B1: Customer Churn Dashboard
B3: Telecom subscription base · 2,000 unique customers · churn rate = Yes ÷ (Yes + No), unknown status excluded
B5: TOTAL CUSTOMERS | G5: CHURN RATE | L5: MONTHLY REVENUE LOST | Q5: ANNUAL REVENUE AT RISK
B6: =[1]Calc!B2 -> 2000 | G6: =[1]Calc!B4 -> 0.33842239 | L6: =[1]Calc!B5 -> 567095 | Q6: =[1]Calc!B6 -> 6805140
B36: KEY INSIGHTS
B37: 1. Contract type is the strongest driver: Month-to-month churn is 47.8% vs 10.9% for Two-year customers.
B38: 2. The first 6 months are critical: 49.7% churn, falling to 8.6% after 4 years. Focus on onboarding and early retention.
B39: 3. Fiber (37.7%) churns more than DSL (28.7%). Review Fiber service quality and pricing.
B40: 4. City and age matter far less (about 29% to 38% across cities, 30% to 37% across ages). Do not target by them.
B41: 5. About ₹68 lakh a year is at risk. Cutting Month-to-month churn by 10 points could save about ₹11 lakh a year.

Sheet analysis of problem with sol.
A1: problem :
A2: i want all detail about this file through buisness insights explain the main points of this data and how can i explain my data tell me every thing mujh proffes
A4: solution:
C5: Check in with new customers: Contact them during their first few months to make sure setup and service are working well.
C6: Resolve problems quickly: Give prompt, proactive support to customers who report service issues or make repeated complaints.
C7: Offer a reason to stay: Provide a reasonable discount or an extra benefit to month-to-month customers who choose an annual plan.
C8: Ask customers for feedback: Find out whether price, service quality, or customer support influenced their decision to leave.
C9: Track churn each month: Measure whether these steps help more customers stay.
C10: Collect more information: The current data shows which customers are more likely to leave, but not why. Customer feedback can help identify the causes.
B13: Additional Business Problems and Recommended Solutions
A15: 1 | B15: High churn among early-tenure customers: Customers in their first six months have a 49.7% churn rate.
B16: Solution: Strengthen onboarding, check in with customers during the first few months, and resolve setup or service issues quickly.
A18: 2 | B18: Higher churn among fiber customers: Fiber customers have a 37.7% churn rate, compared with 28.7% for DSL customers.
B19: Solution: Review fiber customers’ service quality, pricing, and complaint history to identify possible issues before choosing a retention action.
A21: 3 | B21: Churn is concentrated in month-to-month plans: These customers make up 77.6% of known churned customers and account for about 76.8% of the monthly charges linked to churned accounts.
B22: Solution: Offer suitable plan options or benefits to encourage customers to stay, and track whether the offers are cost-effective.
A24: 4 | B24: Some customer information is missing or estimated: The file contains unknown churn statuses and values marked as imputed.
B25: Solution: Improve data collection and validation, and clearly flag estimated values when reporting results.
A27: 5 | B27: The reasons and timing of churn are not recorded: The workbook shows which customers left, but not when they left or why.
B28: Solution: Record cancellation dates and reasons, then review churn by month and customer group.
A30: 6 | B30: Churn rates differ across cities: For example, Chennai’s rate is 38.1%, while Kolkata’s is 28.8%.
B31: Solution: Investigate local service or customer-support issues, while treating these figures as signals to explore rather than confirmed causes.
A33: 7 | B33: Price may be worth investigating: Churned customers’ average monthly charge is slightly higher than retained customers’. This does not prove that price caused churn.
B34: Solution: Ask customers about price and perceived value, then test any pricing changes with a small customer group.
B36: Note: These findings highlight areas for investigation. The workbook does not establish the causes of churn, so customer feedback and service data are needed before deciding on specific changes.
A40: ABOUT THIS PROJECT:
C42: "I analysed a telecom subscription business that was losing one in three customers, which put about ₹68 lakh a year in revenue at risk.
C43: I cleaned a messy dataset of 2,000 customers, analysed it in Excel using formulas and pivot tables, and built a dashboard
C44: I found that churn is driven mainly by contract type and early tenure: Month-to-month customers churn at 47.8% compared with 10.9% for two-year customers, and nearly half of new customers leave within six months.
C45: My recommendation is to move customers onto longer contracts and strengthen onboarding, which could save roughly ₹11 lakh a year."
B47: 1. Business problem
B49: "The company's churn rate is 33.8%.Put differently, it loses about ₹5.7 lakh in monthly billing, or roughly₹68 lakh a year, to customers who leave.
B50: The question I set out to answer was: who is leaving, why, and what can the business do about it?"
B52: 2. Data and approach
B54: "The raw file had 2,058 rows with serious quality issues: 50 duplicate customers, blank rows, mixed date formats, prices stored as text, impossible ages and tenures, and inconsistent labels like 'Dehli' and 'Bengaluru'.
B55: I cleaned it down to 2,000 unique customers and documented every fix in an issues log. Where values were missing,
B56: I rebuilt them from related fields when possible, for example Total Charges equals Monthly Charges times Tenure, and I did not guess the churn status itself."
B58: 3. Key findings
B60: "First, contract type is the strongest driver. Month-to-month customers churn at 47.8%, versus 20.2% for one-year and 10.9% for two-year contracts.
B61: They also make up 78% of all churned customers.
B62: Second, the first six months are critical. Churn is 49.7% in months 0 to 6, and it falls steadily to 8.6% for customers beyond four years.
B63: Third, Fiber has the highest churn among services at 37.7%, compared with 28.7% for DSL. That matters because Fiber is the premium product.
... B78: A natural next step is a predictive model that scores each customer's churn risk, so the retention team can contact the highest-risk customers first."
C81: Finding | D81: Recommendation
C82: Month-to-month churn is 47.8% | D82: Offer discounts or perks for 12-month plans
C83: 49.7% churn in the first 6 months | D83: Welcome offer, onboarding call at day 30, early-warning check
C84: Fiber churn is 37.7% | D84: Investigate network quality and pricing
C85: 2 of the top 10 customers churned (₹80,000+ each) | D85: Personal win-back calls for high-value churners
C86: City and age effects are weak | D86: Don't target by them; reduce wasted effort
A88: "What was the hardest part?"
B90: "Data cleaning. Deciding how to treat missing values was a judgement call.I rebuilt values where the relationship was exact, filled age with the median and flagged it
B91: and left churn status as 'Unknown' instead of guessing it, because it is the target I'm analysing."
A93: "Why did you exclude Unknown churn from the rate?"
B95: "Because we don't know whether those 35 customers left. Including them would understate the churn rate, 33.25% instead of 33.84%."
A97: "How do you know contract type causes churn?"
B99: "I don't. It's a strong association. Customers who are unhappy may avoid long contracts in the first place. To test cause, the business could run an A/B test with a discount for longer contracts."
A101: "What would you do next?"
B103: "Build a churn prediction model, using tenure, contract, service type and charges, and then rank customers by risk and revenue at risk."
A105: "What would you do differently?"
B107: "Get more history (monthly usage, support tickets, complaints), because behaviour before leaving is often a stronger predictor than demographics."
B111: "This was a practice project on a simulated telecom dataset, designed to mirror real-world data problems."

Sheet calculations
A1: KPIs
A2: Total customers | B2: =COUNTA([1]Data!$A$2:$A$2001) -> 2000
A3: Churned customers | B3: =COUNTIF([1]Data!$L$2:$L$2001,"Yes") -> 665
A4: Churn rate | B4: =B3/(B3+COUNTIF([1]Data!$L$2:$L$2001,"No")) -> 0.33842239
A5: Monthly revenue lost | B5: =SUMIFS([1]Data!$H$2:$H$2001,[1]Data!$L$2:$L$2001,"Yes") -> 567095
A6: Annual revenue at risk | B6: =B5*12 -> 6805140
A7: Contract Type
A8: Group | B8: Yes | C8: No | D8: Churn rate | E8: Overall avg
A9: Month-to-month | B9: =COUNTIFS([1]Data!$F$2:$F$2001,$A9,[1]Data!$L$2:$L$2001,"Yes") -> 516 | C9: =COUNTIFS([1]Data!$F$2:$F$2001,$A9,[1]Data!$L$2:$L$2001,"No") -> 564 | D9: =B9/(B9+C9) -> 0.47777778 | E9: =$B$4 -> 0.33842239
A10: One year | B10: =COUNTIFS([1]Data!$F$2:$F$2001,$A10,[1]Data!$L$2:$L$2001,"Yes") -> 99 | C10: =COUNTIFS([1]Data!$F$2:$F$2001,$A10,[1]Data!$L$2:$L$2001,"No") -> 392 | D10: =B10/(B10+C10) -> 0.20162933 | E10: =$B$4 -> 0.33842239
A11: Two year | B11: =COUNTIFS([1]Data!$F$2:$F$2001,$A11,[1]Data!$L$2:$L$2001,"Yes") -> 40 | C11: =COUNTIFS([1]Data!$F$2:$F$2001,$A11,[1]Data!$L$2:$L$2001,"No") -> 328 | D11: =B11/(B11+C11) -> 0.10869565 | E11: =$B$4 -> 0.33842239
A14: Internet Service
A15: Group | B15: Yes | C15: No | D15: Churn rate | E15: Overall avg
A16: DSL | B16: =COUNTIFS([1]Data!$J$2:$J$2001,$A16,[1]Data!$L$2:$L$2001,"Yes") -> 196 | C16: =COUNTIFS([1]Data!$J$2:$J$2001,$A16,[1]Data!$L$2:$L$2001,"No") -> 488 | D16: =B16/(B16+C16) -> 0.28654971 | E16: =$B$4 -> 0.33842239
A17: Fiber | B17: =COUNTIFS([1]Data!$J$2:$J$2001,$A17,[1]Data!$L$2:$L$2001,"Yes") -> 328 | C17: =COUNTIFS([1]Data!$J$2:$J$2001,$A17,[1]Data!$L$2:$L$2001,"No") -> 541 | D17: =B17/(B17+C17) -> 0.37744534 | E17: =$B$4 -> 0.33842239
A18: No Internet | B18: =COUNTIFS([1]Data!$J$2:$J$2001,$A18,[1]Data!$L$2:$L$2001,"Yes") -> 130 | C18: =COUNTIFS([1]Data!$J$2:$J$2001,$A18,[1]Data!$L$2:$L$2001,"No") -> 240 | D18: =B18/(B18+C18) -> 0.35135135 | E18: =$B$4 -> 0.33842239
A21: City
A22: Group | B22: Yes | C22: No | D22: Churn rate | E22: Overall avg
A23: Chennai | B23: =COUNTIFS([1]Data!$E$2:$E$2001,$A23,[1]Data!$L$2:$L$2001,"Yes") -> 48 | C23: =COUNTIFS([1]Data!$E$2:$E$2001,$A23,[1]Data!$L$2:$L$2001,"No") -> 78 | D23: =B23/(B23+C23) -> 0.38095238 | E23: =$B$4 -> 0.33842239
A24: Indore | B24: =COUNTIFS([1]Data!$E$2:$E$2001,$A24,[1]Data!$L$2:$L$2001,"Yes") -> 51 | C24: =COUNTIFS([1]Data!$E$2:$E$2001,$A24,[1]Data!$L$2:$L$2001,"No") -> 86 | D24: =B24/(B24+C24) -> 0.37226277 | E24: =$B$4 -> 0.33842239
A25: Chandigarh | B25: =COUNTIFS([1]Data!$E$2:$E$2001,$A25,[1]Data!$L$2:$L$2001,"Yes") -> 50 | C25: =COUNTIFS([1]Data!$E$2:$E$2001,$A25,[1]Data!$L$2:$L$2001,"No") -> 87 | D25: =B25/(B25+C25) -> 0.3649635 | E25: =$B$4 -> 0.33842239
A26: Mumbai | B26: =COUNTIFS([1]Data!$E$2:$E$2001,$A26,[1]Data!$L$2:$L$2001,"Yes") -> 47 | C26: =COUNTIFS([1]Data!$E$2:$E$2001,$A26,[1]Data!$L$2:$L$2001,"No") -> 82 | D26: =B26/(B26+C26) -> 0.36434109 | E26: =$B$4 -> 0.33842239
A27: Lucknow | B27: =COUNTIFS([1]Data!$E$2:$E$2001,$A27,[1]Data!$L$2:$L$2001,"Yes") -> 50 | C27: =COUNTIFS([1]Data!$E$2:$E$2001,$A27,[1]Data!$L$2:$L$2001,"No") -> 91 | D27: =B27/(B27+C27) -> 0.35460993 | E27: =$B$4 -> 0.33842239
A28: Delhi | B28: =COUNTIFS([1]Data!$E$2:$E$2001,$A28,[1]Data!$L$2:$L$2001,"Yes") -> 51 | C28: =COUNTIFS([1]Data!$E$2:$E$2001,$A28,[1]Data!$L$2:$L$2001,"No") -> 93 | D28: =B28/(B28+C28) -> 0.35416667 | E28: =$B$4 -> 0.33842239
A29: Jaipur | B29: =COUNTIFS([1]Data!$E$2:$E$2001,$A29,[1]Data!$L$2:$L$2001,"Yes") -> 48 | C29: =COUNTIFS([1]Data!$E$2:$E$2001,$A29,[1]Data!$L$2:$L$2001,"No") -> 90 | D29: =B29/(B29+C29) -> 0.34782609 | E29: =$B$4 -> 0.33842239
A30: Hyderabad | B30: =COUNTIFS([1]Data!$E$2:$E$2001,$A30,[1]Data!$L$2:$L$2001,"Yes") -> 46 | C30: =COUNTIFS([1]Data!$E$2:$E$2001,$A30,[1]Data!$L$2:$L$2001,"No") -> 88 | D30: =B30/(B30+C30) -> 0.34328358 | E30: =$B$4 -> 0.33842239
A31: Kochi | B31: =COUNTIFS([1]Data!$E$2:$E$2001,$A31,[1]Data!$L$2:$L$2001,"Yes") -> 51 | C31: =COUNTIFS([1]Data!$E$2:$E$2001,$A31,[1]Data!$L$2:$L$2001,"No") -> 98 | D31: =B31/(B31+C31) -> 0.34228188 | E31: =$B$4 -> 0.33842239
A32: Bhopal | B32: =COUNTIFS([1]Data!$E$2:$E$2001,$A32,[1]Data!$L$2:$L$2001,"Yes") -> 42 | C32: =COUNTIFS([1]Data!$E$2:$E$2001,$A32,[1]Data!$L$2:$L$2001,"No") -> 81 | D32: =B32/(B32+C32) -> 0.34146341 | E32: =$B$4 -> 0.33842239
A33: Pune | B33: =COUNTIFS([1]Data!$E$2:$E$2001,$A33,[1]Data!$L$2:$L$2001,"Yes") -> 44 | C33: =COUNTIFS([1]Data!$E$2:$E$2001,$A33,[1]Data!$L$2:$L$2001,"No") -> 96 | D33: =B33/(B33+C33) -> 0.31428571 | E33: =$B$4 -> 0.33842239
A34: Ahmedabad | B34: =COUNTIFS([1]Data!$E$2:$E$2001,$A34,[1]Data!$L$2:$L$2001,"Yes") -> 43 | C34: =COUNTIFS([1]Data!$E$2:$E$2001,$A34,[1]Data!$L$2:$L$2001,"No") -> 103 | D34: =B34/(B34+C34) -> 0.29452055 | E34: =$B$4 -> 0.33842239
... A36: Kolkata | B36: =COUNTIFS([1]Data!$E$2:$E$2001,$A36,[1]Data!$L$2:$L$2001,"Yes") -> 40 | C36: =COUNTIFS([1]Data!$E$2:$E$2001,$A36,[1]Data!$L$2:$L$2001,"No") -> 99 | D36: =B36/(B36+C36) -> 0.28776978 | E36: =$B$4 -> 0.33842239
A39: Tenure
A40: Group | B40: Yes | C40: No | D40: Churn rate | E40: Overall avg
A41: 0-6 mo | B41: =COUNTIFS([1]Data!$M$2:$M$2001,$A41,[1]Data!$L$2:$L$2001,"Yes") -> 184 | C41: =COUNTIFS([1]Data!$M$2:$M$2001,$A41,[1]Data!$L$2:$L$2001,"No") -> 186 | D41: =B41/(B41+C41) -> 0.4972973 | E41: =$B$4 -> 0.33842239
A42: 7-12 mo | B42: =COUNTIFS([1]Data!$M$2:$M$2001,$A42,[1]Data!$L$2:$L$2001,"Yes") -> 153 | C42: =COUNTIFS([1]Data!$M$2:$M$2001,$A42,[1]Data!$L$2:$L$2001,"No") -> 248 | D42: =B42/(B42+C42) -> 0.38154613 | E42: =$B$4 -> 0.33842239
A43: 13-24 mo | B43: =COUNTIFS([1]Data!$M$2:$M$2001,$A43,[1]Data!$L$2:$L$2001,"Yes") -> 261 | C43: =COUNTIFS([1]Data!$M$2:$M$2001,$A43,[1]Data!$L$2:$L$2001,"No") -> 485 | D43: =B43/(B43+C43) -> 0.34986595 | E43: =$B$4 -> 0.33842239
A44: 25-48 mo | B44: =COUNTIFS([1]Data!$M$2:$M$2001,$A44,[1]Data!$L$2:$L$2001,"Yes") -> 48 | C44: =COUNTIFS([1]Data!$M$2:$M$2001,$A44,[1]Data!$L$2:$L$2001,"No") -> 242 | D44: =B44/(B44+C44) -> 0.16551724 | E44: =$B$4 -> 0.33842239
A45: 49+ mo | B45: =COUNTIFS([1]Data!$M$2:$M$2001,$A45,[1]Data!$L$2:$L$2001,"Yes") -> 12 | C45: =COUNTIFS([1]Data!$M$2:$M$2001,$A45,[1]Data!$L$2:$L$2001,"No") -> 128 | D45: =B45/(B45+C45) -> 0.085714286 | E45: =$B$4 -> 0.33842239
A48: Age Group
A49: Group | B49: Yes | C49: No | D49: Churn rate | E49: Overall avg
A50: 18-25 yrs | B50: =COUNTIFS([1]Data!$N$2:$N$2001,$A50,[1]Data!$L$2:$L$2001,"Yes") -> 85 | C50: =COUNTIFS([1]Data!$N$2:$N$2001,$A50,[1]Data!$L$2:$L$2001,"No") -> 172 | D50: =B50/(B50+C50) -> 0.3307393 | E50: =$B$4 -> 0.33842239
A51: 26-35 yrs | B51: =COUNTIFS([1]Data!$N$2:$N$2001,$A51,[1]Data!$L$2:$L$2001,"Yes") -> 100 | C51: =COUNTIFS([1]Data!$N$2:$N$2001,$A51,[1]Data!$L$2:$L$2001,"No") -> 230 | D51: =B51/(B51+C51) -> 0.3030303 | E51: =$B$4 -> 0.33842239
A52: 36-45 yrs | B52: =COUNTIFS([1]Data!$N$2:$N$2001,$A52,[1]Data!$L$2:$L$2001,"Yes") -> 121 | C52: =COUNTIFS([1]Data!$N$2:$N$2001,$A52,[1]Data!$L$2:$L$2001,"No") -> 204 | D52: =B52/(B52+C52) -> 0.37230769 | E52: =$B$4 -> 0.33842239
A53: 46-60 yrs | B53: =COUNTIFS([1]Data!$N$2:$N$2001,$A53,[1]Data!$L$2:$L$2001,"Yes") -> 188 | C53: =COUNTIFS([1]Data!$N$2:$N$2001,$A53,[1]Data!$L$2:$L$2001,"No") -> 379 | D53: =B53/(B53+C53) -> 0.33156966 | E53: =$B$4 -> 0.33842239
A54: 60+ yrs | B54: =COUNTIFS([1]Data!$N$2:$N$2001,$A54,[1]Data!$L$2:$L$2001,"Yes") -> 171 | C54: =COUNTIFS([1]Data!$N$2:$N$2001,$A54,[1]Data!$L$2:$L$2001,"No") -> 315 | D54: =B54/(B54+C54) -> 0.35185185 | E54: =$B$4 -> 0.33842239
